Workbook

Sheet README
A1: Validation of the object → EuroVoc mapping (Step 7)
A3: What to do
A4: 1. Go to the Validate sheet. Every row is part of the sample; the order is random.
A5: 2. Fill in the yellow columns: judgement (drop-down), Optional: better_concept (optional), notes.
A6: 3. Judge candidate 1 mainly, for the object as used in the context; use candidates 2-3 to decide 'partial'. | B6: JUDGE object vs cand_1
A7: 4. Leave the 'key' sheet alone until you are done; it holds the scores you should not see.
A8: 5. When finished, save and run: python eurovoc_review.py review --xlsx <this file>
A10: Judgement codes
A11: correct – candidate 1 is the right concept, or an acceptable close one.
A12: partial – candidate 1 is in the right area but too broad/narrow, or a lower candidate is right.
A13: wrong – no candidate fits the object.
A14: unclear – the object itself cannot be judged (placeholder, fragment, unresolved reference).
A16: Special rows
A17: Rows with several numbered contexts are frequent texts judged once for all their uses: judge the
A18: usual use; if the mapping fits some uses but not others, choose 'partial' and note it.
A19: Rows without candidates (only if checks were drawn): the object was left unmapped or dropped.
A20: correct = rightly so; wrong = a EuroVoc concept clearly exists / a real object was lost.
... A29: Example of a filled-in row (not part of the data)
A30: object | B30: cand_1 | C30: cand_2 | D30: judgement | E30: better_concept | F30: notes
A31: informatie | B31: informatie | C31: overdracht van informatie | D31: correct | F31: generic, but the concept matches

Sheet Validate
A1: row | B1: object | C1: raw_object | D1: cand_1 | E1: cand_2 | F1: cand_3 | G1: n_norms | H1: context | I1: judgement | J1: better_concept | K1: notes | L1: norm_id
A2: 1 | B2: verhouding tot het ICT-risico van de financiële entiteit | C2: in verhouding tot het ICT-risico van de financiële entiteit | D2: gevolgen van ICT | G2: 1 | H2: …is, vaardigheden en deskundigheid op het gebied van ICT-risico en over de nodige onafhankelijkheid. De frequentie en de focus van de ICT-audits staan in verhouding tot het ICT-risico van de financiële entiteit. | L2: 32022R2554:6:6:15
A3: 2 | B3: verplichtingen | D3: contract | G3: 27 | H3: [1] EU 32016R0679:30:5:7: De in de leden 1 en 2 bedoelde verplichtingen zijn niet van toepassing op ondernemingen of organisaties die minder dan 250 personen in dienst hebben, tenzij het waarschijnlijk is dat de verwerkin… [2] NL BWBR0009950:6.3:1:2: …ment en Markt kan met het oog op de doelstellingen, bedoeld in artikel 3, tweede en vierde lid, van richtlijn (EU) 2018/1972, op een redelijk verzoek verplichtingen opleggen om toegang te verlenen tot: a. kabels of bijbehorende faciliteiten binnen gebouwen of, b. indien het dichtst bij het netwerkaansluitpunt gel… [3] EU 32024R1689:53:2:8: De in lid 1, punten a) en b) genoemde verplichtingen gelden niet voor aanbieders van AI-modellen die worden vrijgegeven in het kader van een vrije en opensource licentie die de raadpleging, het gebruik,… | L3: 32016R0679:30:5:7, BWBR0009950:6.3:1:2, 32024R1689:53:2:8
A4: 3 | B4: misbruik | C4: vertraging of misbruik van het overstapproces | D4: rechtsmisbruik | E4: mishandeling | F4: machtsmisbruik | G4: 2 | H4: …e dat de levering niet langer dan één werkdag wordt onderbroken; c. werken te goeder trouw samen ten behoeve van het overstappen; d. veroorzaken geen vertraging of misbruik van het overstapproces, en e. zorgen ervoor dat het overstappen niet plaatsvindt zonder uitdrukkelijke toestemming van de abonnee. | L4: BWBR0009950:7.2c:2:3
A5: 4 | B5: informatie | D5: informatie | G5: 87 | H5: [1] EU 32024R1689:70:2:6: De lidstaten verstrekken de Commissie informatie over de identiteit en de taken van de aanmeldende autoriteiten en de markttoezichtautoriteiten, alsook over eventuele latere wijzigingen daarin. De l… [2] NL BWBR0009950:6a.9:1:2: …toriteit Consument en Markt kan op grond artikel 6a.2, eerste lid, de verplichting opleggen om door de Autoriteit Consument en Markt nader te bepalen informatie met betrekking tot door de Autoriteit Consument en Markt te bepalen vormen van toegang bekend te maken. Deze informatie kan onder meer betrekking heb… [3] EU 32016R0679:12:1:4: De verwerkingsverantwoordelijke neemt passende maatregelen opdat de betrokkene de in de artikelen 13 en 14 bedoelde informatie en de in de artikelen 15 tot en met 22 en artikel 34 bedoelde communicatie in verband met de verwerking in een beknopte, transparante, begrijpelijke … | L5: 32024R1689:70:2:6, BWBR0009950:6a.9:1:2, 32016R0679:12:1:4
A6: 5 | B6: nummergebruiker | C6: de nummergebruiker | D6: computergebruiker | E6: informatiegebruiker | G6: 2 | H6: De Autoriteit Consument en Markt stelt de nummergebruiker, voorzover deze bij de Autoriteit Consument en Markt bekend is, van de aanwijzing op de hoogte. | L6: BWBR0009950:7.3a:4:4
A7: 6 | B7: Archiefbescheiden van de Autoriteit Consument en Markt | C7: Archiefbescheiden van de Autoriteit Consument en Markt en aanvragen als bedoeld in het tweede lid | D7: Instituut voor de gezondheid en de veiligheid van de consument | E7: Europese Autoriteit voor effecten en markten | F7: Uitvoerend Agentschap voor consumenten, gezondheid, landbouw en voeding | G7: 1 | H7: Archiefbescheiden van de Autoriteit Consument en Markt en aanvragen als bedoeld in het tweede lid, worden overgedragen aan Onze Minister, voor zover zij niet overeenkomstig de Archiefwet 1995 zijn overgebracht naar een archiefbewaarplaats. | L7: BWBR0009950:20.15a:4:2
A8: 7 | B8: termijn | D8: procestermijn | E8: termijn voor publicatie | F8: terminologie | G8: 23 | H8: [1] EU 32022L2555:38:6:9: …de handeling aan het Europees Parlement en de Raad bezwaar heeft gemaakt, of indien zowel het Europees Parlement als de Raad voor het verstrijken van die termijn de Commissie hebben meegedeeld dat zij daartegen geen bezwaar zullen maken. Die termijn wordt op initiatief van het Europees Parlement of de Raad met… [2] NL BWBR0009950:14a.2:3:5: … na ontvangst van de melding of een verbod op grond van artikel 14a.4, eerste lid, wordt opgelegd. Indien nader onderzoek nodig is, kan Onze Minister de termijn verlengen met zes maanden. De termijn wordt opgeschort met ingang van de dag: a. waarop Onze Minister aanvullende informatie verzoekt tot de dag waar… [3] EU 32024R1689:80:2:4: …deze alle nodige maatregelen neemt om het AI-systeem in overeenstemming te brengen met de vereisten en verplichtingen van deze verordening, en binnen een termijn die de markttoezichtautoriteit kan voorschrijven passende corrigerende maatregelen neemt. | L8: 32022L2555:38:6:9, BWBR0009950:14a.2:3:5, 32024R1689:80:2:4
A9: 8 | B9: nadere regels | D9: betere regelgeving | G9: 54 | H9: [1] EU 32016R0679:88:1:1: Bij wet of bij collectieve overeenkomst kunnen de lidstaten nadere regels vaststellen ter bescherming van de rechten en vrijheden met betrekking tot de verwerking van de persoonsgegevens van werknemers in het kader van de a… [2] NL BWBR0009950:7.7:4:3: Bij of krachtens algemene maatregel van bestuur kunnen nadere regels worden gesteld met betrekking tot de in het derde lid bedoelde voorzieningen. [3] NL BWBR0052872:50:4:5: Bij regeling van Onze Minister van Economische Zaken kunnen nadere regels worden gesteld ten aanzien van het bepaalde in dit artikel. | L9: 32016R0679:88:1:1, BWBR0009950:7.7:4:3, BWBR0052872:50:4:5
A10: 9 | B10: beperkingen | C10: voorschriften en beperkingen | D10: beperking van bewegingsvrijheid | E10: verplichting | F10: beroepsverbod | G10: 13 | H10: Onze Minister kan aan de transitievergunning voorschriften en beperkingen verbinden, waaronder het voorschrift uitsluitend frequentieruimte te gebruiken in overeenstemming met de afspraken in de transitieovereenkomst bedoel… | L10: BWBR0009950:3.8a:4:9
A11: 10 | B11: onregelmatigheden | C11: onregelmatigheden, storingen en onverwachte prestaties | D11: onverkiesbaarheid | E11: onverdeeldheid | F11: ontvankelijkheid | G11: 3 | H11: …m met een hoog risico goed te begrijpen en de werking ervan naar behoren te kunnen monitoren, onder meer met het oog op het opsporen en aanpakken van onregelmatigheden, storingen en onverwachte prestaties; b) zich bewust te blijven van de mogelijke neiging om automatisch of te veel te vertrouwen op de output van een AI-systeem met een hoog risico (de z… | L11: 32024R1689:14:4:16
A12: 11 | B12: bijstand | D12: rechtsbijstand | E12: opstand | F12: rechtstoestand | G12: 14 | H12: … volgende taken: a. het monitoren en analyseren van cyberdreigingen, kwetsbaarheden en incidenten op nationaal niveau, en het op verzoek verlenen van bijstand aan de betrokken essentiële entiteit of belangrijke entiteit met betrekking tot het realtime of bijna-realtime monitoren van haar netwerk- en informa… | L12: BWBR0052872:16:2:4
A13: 12 | B13: toestemming | D13: verkoopvergunning | E13: wapenvergunning | F13: besluit | G13: 18 | H13: [1] EU 32016R0679:58:3:30: …ellingen en organen alsmede aan het publiek advies te verstrekken over aangelegenheden die verband houden met de bescherming van persoonsgegevens; c) toestemming te geven voor verwerking als bedoeld in artikel 36, lid 5, indien die voorafgaande toestemming door het lidstatelijke recht wordt voorgeschreven; d) … [2] NL BWBR0009950:3.20a:7:8: In afwijking van het eerste lid is toestemming niet vereist in bij of krachtens algemene maatregel van bestuur aan te wijzen gevallen. [3] EU 32016R0679:7:3:4: De betrokkene heeft het recht zijn toestemming te allen tijde in te trekken. Het intrekken van de toestemming laat de rechtmatigheid van de verwerking op basis van de toestemming vóór de intrekkin… | L13: 32016R0679:58:3:30, BWBR0009950:3.20a:7:8, 32016R0679:7:3:4
A14: 13 | B14: voorschriften | D14: verordening | G14: 35 | H14: [1] EU 32024R1689:99:1:1: Overeenkomstig de voorwaarden van deze verordening stellen de lidstaten de voorschriften vast voor sancties en andere handhavingsmaatregelen, die ook waarschuwingen en niet-monetaire maatregelen kunnen omvatten, die van toepassing zijn op… [2] NL BWBR0009950:7.9:whole:1: Bij ministeriële regeling kunnen voorschriften worden gesteld met betrekking tot het door een aanbieder van een openbaar elektronisch communicatienetwerk of openbare elektronische communicatiedien… [3] EU 32016R0679:43:6:13: De in lid 3 van dit artikel bedoelde voorschriften en de in artikel 42, lid 5, bedoelde criteria worden door de toezichthoudende autoriteit in een eenvoudig toegankelijke vorm openbaar gemaakt. De toezichthoudende autoriteiten delen die eisen en … | L14: 32024R1689:99:1:1, BWBR0009950:7.9:whole:1, 32016R0679:43:6:13
A15: 14 | B15: aanmelding | C15: de aanmelding | D15: aanklacht | E15: bekendmaking | F15: formulier | G15: 2 | H15: Wanneer de Commissie vaststelt dat een aangemelde instantie niet of niet meer aan de aanmeldingseisen voldoet, brengt zij de aanmeldende lidstaat daarvan op de hoogte en verzoekt zij deze lidstaat de nodige corrigerende maatregelen te nemen, en … | L15: 32024R1689:37:4:11
A16: 15 | B16: verordening | C16: deze verordening | D16: verordening | E16: verordening (EU) | G16: 3 | H16: …intrekking van die certificering leidt, onverminderd de verantwoordelijkheid van de verwerkingsverantwoordelijke of de verwerker voor de naleving van deze verordening. De accreditatie wordt afgegeven voor een maximumperiode van vijf jaar en kan onder dezelfde voorwaarden worden verlengd, mits het certificeringsorga… | L16: 32016R0679:43:4:11
A17: 16 | B17: vertaling van relevante informatie | C17: de vertaling van relevante informatie | D17: vertaling | G17: 1 | H17: …; c) de communicatie met andere instellingen en het brede publiek; d) het gebruik van elektronische middelen voor interne en externe communicatie; e) de vertaling van relevante informatie; f) de voorbereiding en follow-up van de bijeenkomsten van het Comité; g) de voorbereiding, opstelling en bekendmaking van adviezen, besluiten inzake… | L17: 32016R0679:75:6:9
A18: 17 | B18: erkenning | C18: Een erkenning | D18: bekendmaking | E18: beginsel van wederzijdse erkenning | F18: schenking | G18: 9 | H18: Een erkenning kan op verzoek van de erkende dienst worden ingetrokken. De erkende dienst voegt bij zijn verzoek een beëindigingsplan. Bij ministeriële regeling kun… | L18: BWBR0048156:14:1:3
A19: 18 | B19: verzoek | C19: aan het verzoek | D19: verplichting | E19: beschikking | F19: oproepen van gegevens | G19: 14 | H19: …t verstrekken van de gevraagde informatie of communicatie en het treffen van de gevraagde maatregelen gepaard gaan; ofwel b) weigeren gevolg te geven aan het verzoek. Het is aan de verwerkingsverantwoordelijke om de kennelijk ongegronde of buitensporige aard van het verzoek aan te tonen. | L19: 32016R0679:12:5:17
A20: 19 | B20: geaggregeerde beoordeling van het volwassenheidsniveau van de cyberbeveiligingscapaciteiten en -middelen in de hele Unie, met inbegrip van die op sectorniveau | C20: een geaggregeerde beoordeling van het volwassenheidsniveau van de cyberbeveiligingscapaciteiten en -middelen in de hele Unie, met inbegrip van die op sectorniveau, en van de mate waarin de nationale cyberbeveiligingsstrategieën van de lidstaten op elkaar zijn afgestemd | D20: weerbaarheid op het gebied van cyberbeveiliging | G20: 1 | H20: …p van kleine en middelgrote ondernemingen; d) een geaggregeerde beoordeling van het resultaat van de in artikel 19 bedoelde collegiale toetsingen; e) een geaggregeerde beoordeling van het volwassenheidsniveau van de cyberbeveiligingscapaciteiten en -middelen in de hele Unie, met inbegrip van die op sectorniveau, en van de mate waarin de nationale cyberbeveiligingsstrategieën van de lidstaten op elkaar zijn afgestemd. | L20: 32022L2555:18:1:9
A21: 20 | B21: elementen | C21: de in lid 2 bedoelde elementen | D21: profielen | E21: programmeren | F21: nanomaterialen | G21: 7 | H21: …is met betrekking tot de periode en de geografische en personele werkingssfeer. Bij haar beslissing over het verzoek houdt die instantie rekening met de in lid 2 bedoelde elementen. Een besluit dat nadelige rechtsgevolgen heeft voor een persoon mag niet uitsluitend worden genomen op basis van de output van het systeem voor biome… | L21: 32024R1689:5:3:18
A22: 21 | B22: bevoegde autoriteit | C22: de betrokken bevoegde autoriteit, bedoeld in artikel 8 van de Wet weerbaarheid kritieke entiteiten | D22: bevoegde nationale autoriteit | E22: verordenende bevoegdheid | F22: administratieve bevoegdheid | G22: 8 | H22: De betrokken bevoegde autoriteit, bedoeld in artikel 15, stelt de betrokken bevoegde autoriteit, bedoeld in artikel 8 van de Wet weerbaarheid kritieke entiteiten, op de hoogte van haar beoordeling van de naleving van het bepaalde bij of krachtens deze wet door een essentiële entiteit die tevens kritieke entite… | L22: BWBR0052872:56:2:3
A23: 22 | B23: AI-bureau | C23: het AI-bureau | D23: informatiebureau | E23: Publicatiebureau | F23: kantoorautomatisering | G23: 3 | H23: …bevoegdheden voor toezicht op en handhaving van hoofdstuk V, rekening houdend met de procedurele waarborgen krachtens artikel 94. De Commissie belast het AI-bureau met de uitvoering van deze taken, onverminderd de organisatiebevoegdheden van de Commissie en de bevoegdheidsverdeling tussen de lidstaten en de Unie… | L23: 32024R1689:88:1:2
A24: 23 | B24: risico | C24: op de relevante omstandigheden en risico’s | D24: risicomanagement | G24: 3 | H24: …van het systeem. De technische oplossingen die gericht zijn op het waarborgen van de cyberbeveiliging van AI-systemen met een hoog risico sluiten aan op de relevante omstandigheden en risico’s. De technische oplossingen voor het aanpakken van AI-specifieke kwetsbaarheden omvatten, waar passend, maatregelen voor het voorkomen, traceren, reag… | L24: 32024R1689:15:5:13
A25: 24 | B25: uitvoeringshandelingen | D25: uitvoeringsverordening | E25: uitvoeringsbesluit | F25: uitvoeringsrichtlijn | G25: 24 | H25: [1] EU 32022L2555:23:11:35: …delingen vast waarin nader wordt gespecificeerd in welke gevallen een incident als significant wordt beschouwd als bedoeld in lid 3. De Commissie kan dergelijke uitvoeringshandelingen vaststellen met betrekking tot andere essentiële en belangrijke entiteiten. De Commissie wisselt advies uit en werkt samen met de samenwerkingsgroep … [2] EU 32022L2555:21:5:14: Uiterlijk op 17 oktober 2024 stelt de Commissie uitvoeringshandelingen vast met de technische en methodologische vereisten van de in lid 2 bedoelde maatregelen met betrekking tot DNS-dienstverleners, registers voor tople… [3] EU 32016R0679:45:5:8: …bij uitvoeringshandelingen zonder terugwerkende kracht over tot intrekking, wijziging of schorsing van het in lid 3 van dit artikel bedoelde besluit. Die uitvoeringshandelingen worden vastgesteld volgens de in artikel 93, lid 2, bedoelde onderzoeksprocedure. Om naar behoren gemotiveerde dwingende redenen van urgentie, stelt … | L25: 32022L2555:23:11:35, 32022L2555:21:5:14, 32016R0679:45:5:8
A26: 25 | B26: effecten van de wijziging in de praktijk | C26: een verslag over de doeltreffendheid en de effecten van de wijziging van de artikelen 13.2a, 13.4 en 13.5 in de praktijk | D26: effecten van de digitale revolutie | E26: wijziging van het ministerie | G26: 1 | H26: …t in overeenstemming met Onze Minister binnen drie jaar na de inwerkingtreding van deze wet en vervolgens telkens na drie jaar aan de Staten-Generaal een verslag over de doeltreffendheid en de effecten van de wijziging van de artikelen 13.2a, 13.4 en 13.5 in de praktijk, voor zover die wijzigingen betrekking hebben op de implementatie van Richtlijn nr 2006/24/EG van het Europees Parlement en de Raad van de Europese U… | L26: BWBR0009950:13.9:whole:1
A27: 26 | B27: maatregelen | D27: bestuursmaatregel | E27: beheer | F27: besluit | G27: 27 | H27: [1] EU 32016R0679:34:3:5: …eist wanneer een van de volgende voorwaarden is vervuld: a) de verwerkingsverantwoordelijke heeft passende technische en organisatorische beschermingsmaatregelen genomen en deze maatregelen zijn toegepast op de persoonsgegevens waarop de inbreuk in verband met persoonsgegevens betrekking heeft, met name die we… [2] NL BWBR0009950:7.4:3:6: …diensten volledige, vergelijkbare, betrouwbare, gebruiksvriendelijke en actuele informatie bekend te maken over: a. de kwaliteit van hun diensten; b. de maatregelen die zijn genomen om gelijkwaardige toegang voor eindgebruikers met een handicap te waarborgen; c. de afhankelijkheid van de kwaliteit van de dienstverlening van externe factoren, indien van toepassing en indien de eindgebruikers consumenten zi… [3] EU 32016R0679:28:3:9: …n zich ertoe hebben verbonden vertrouwelijkheid in acht te nemen of door een passende wettelijke verplichting van vertrouwelijkheid zijn gebonden; c) alle overeenkomstig artikel 32 vereiste maatregelen neemt; d) aan de in de leden 2 en 4 bedoelde voorwaarden voor het in dienst nemen van een andere verwerker voldoet; e) rekening houdend met de aard v… | L27: 32016R0679:34:3:5, BWBR0009950:7.4:3:6, 32016R0679:28:3:9
A28: 27 | B28: elementen | C28: ten minste de volgende elementen | D28: profielen | E28: programmeren | F28: nanomaterialen | G28: 7 | H28: De contractuele overeenkomsten inzake het gebruik van ICT-diensten bevatten ten minste de volgende elementen: a) een duidelijke en volledige beschrijving van alle door de derde aanbieder van ICT-diensten te leveren functies en ICT-diensten, met vermelding of… | L28: 32022R2554:30:2:5
A29: 28 | B29: veiling | C29: een veiling | D29: veiling | G29: 1 | H29: …r overeenkomstig de bij of krachtens deze wet gestelde regels in aanmerking komt, wordt aan deze aanvrager het nummer toegekend zonder toepassing van een veiling. | L29: BWBR0009950:4.2:10:19
A30: 29 | B30: bindende aanwijzing | C30: een bindende aanwijzing | D30: verplicht advies | G30: 3 | H30: De bevoegde autoriteit kan een essentiële entiteit een bindende aanwijzing geven om binnen een daarbij gestelde redelijke termijn de daarin omschreven handelingen te verrichten of de daarin omschreven maatregelen te nemen te… | L30: BWBR0052872:74:whole:1
A31: 30 | B31: belanghebbenden | D31: belangengroep | E31: algemeen belang | F31: medeëigendom | G31: 3 | H31: …n informatie, voor zover er passende waarborgen voor de bescherming van persoonsgegevens en andere grondrechten en fundamentele vrijheden bestaan; c) belanghebbenden te betrekken bij besprekingen en activiteiten om de internationale samenwerking bij de handhaving van de wetgeving inzake de bescherming van persoons… | L31: 32016R0679:50:whole:4
A32: 31 | B32: gebruik laten maken van deze werken | C32: het gebruik laten maken van deze werken | D32: gebruik van robots | G32: 1 | H32: …standgehouden of opgeruimd. Voor de rechthebbende op of de beheerder van de genoemde bovengrondse ondersteuningswerken bestaat geen gedoogplicht voor het gebruik laten maken van deze werken. | L32: BWBR0009950:5.2:6:8
A33: 32 | B33: omvang | C33: de omvang en het algemene risicoprofiel van de financiële entiteit, en met de aard, schaal en complexiteit van de diensten, activiteiten en verrichtingen ervan | D33: omzettingstermijn | G33: 2 | H33: …kader voor ICT-risicobeheer verder te specificeren. Bij het opstellen van die ontwerpen van technische reguleringsnormen houden de ETA’s rekening met de omvang en het algemene risicoprofiel van de financiële entiteit, en met de aard, schaal en complexiteit van de diensten, activiteiten en verrichtingen ervan. De ETA’s leggen deze ontwerpen van technische reguleringsnormen uiterlijk op 17 januari 2024 voor aan de Commissie. Aan de Commissie wordt de bevoeg… | L33: 32022R2554:16:3:19
A34: 33 | B34: verplichting | D34: contract | G34: 38 | H34: [1] EU 32024R1689:57:1:4: … Commissie kan technische ondersteuning, advies en instrumenten verstrekken voor de oprichting en werking van AI-testomgevingen voor regelgeving. Aan de verplichting uit hoofde van de eerste alinea kan ook worden voldaan door deel te nemen aan een bestaande testomgeving, voor zover die deelname de deelnemende lidstaten een gelijkwaardig niveau v… [2] NL BWBR0052872:21a:1:1: …ten die de nationale veiligheid raken te voorkomen, legt hij in overeenstemming met Onze Minister een essentiële entiteit of een belangrijke entiteit de verplichting op om in de daarbij aangewezen onderdelen van haar netwerk- en informatiesystemen uitsluitend gebruik te maken van producten of diensten van anderen … [3] EU 32024R1689:50:2:7: …llende soorten content, de uitvoeringskosten en de algemeen erkende stand van de techniek, zoals tot uiting kan komen in relevante technische normen. Deze verplichting is niet van toepassing voor zover de AI-systemen een ondersteunende functie voor standaardbewerking vervullen of de door de gebruiksverantwoordelijke… | L34: 32024R1689:57:1:4, BWBR0052872:21a:1:1, 32024R1689:50:2:7
A35: 34 | B35: effectieve procedure om onjuiste informatie te melden | C35: in een effectieve procedure om onjuiste informatie te melden | D35: vertrouwelijke informatie | G35: 1 | H35: … duidelijk dat de gepresenteerde informatie geen volledig overzicht van de markt biedt, voordat de zoekresultaten worden getoond; g. de tool voorziet in een effectieve procedure om onjuiste informatie te melden; h. de tool voorziet in de mogelijkheid tot vergelijking van de prijzen, tarieven en kwaliteit van de dienstverlening van de aanbiedingen waartussen … | L35: BWBR0009950:7.3:5:9
A36: 35 | B36: aanvullende verklaring | C36: een aanvullende verklaring | D36: aangevulde realiteit | E36: officiële verklaring | F36: nota van toelichting | G36: 1 | H36: …ming van de doeleinden van de verwerking heeft de betrokkene het recht vervollediging van onvolledige persoonsgegevens te verkrijgen, onder meer door een aanvullende verklaring te verstrekken. | L36: 32016R0679:16:whole:3
A37: 36 | B37: latere wijzigingen | C37: alle latere wijzigingen daarvan | D37: gewijzigd voorstel | E37: invoering van vernieuwingen | G37: 4 | H37: Elke lidstaat deelt de Commissie uiterlijk op 25 mei 2018 de overeenkomstig lid 1 vastgestelde wetgevingsbepalingen mee, alsook onverwijld alle latere wijzigingen daarvan. | L37: 32016R0679:84:2:4
A38: 37 | B38: informatie, alsmede informatie of kan worden verkregen | C38: informatie die voor of tijdens onderhandelingen over interoperabiliteits- of toegangsovereenkomsten aan hen is verstrekt, alsmede informatie die bij de uitvoering van de overeenkomst is of kan worden verkregen | D38: informatie | G38: 2 | H38: Aanbieders van elektronische communicatienetwerken of aanbieders van elektronische communicatiediensten mogen informatie die voor of tijdens onderhandelingen over interoperabiliteits- of toegangsovereenkomsten aan hen is verstrekt, alsmede informatie die bij de uitvoering van de overeenkomst is of kan worden verkregen uitsluitend gebruiken voor het doel waarvoor deze informatie is verstrekt, respectievelijk uitsluitend gebruiken voor de uitvoering van de overeenkom… | L38: BWBR0009950:6.1:2:5
A39: 38 | B39: nummergebruikers | C39: de nummergebruikers | D39: computergebruiker | E39: informatiegebruiker | F39: hulp aan de gebruiker | G39: 1 | H39: Nummerhouders registreren binnen zes maanden na de inwerkingtreding van artikel 4.9, derde lid, onderdeel b, de nummergebruikers. De nummergebruiker krijgt het nummer op de dag van registratie door de nummerhouder van rechtswege in gebruik door de nummerhouder. | L39: BWBR0009950:20.16a:2:1
A40: 39 | B40: automatische waarschuwingsmechanismen | D40: systeem voor tijdige waarschuwing | E40: automatische informatieverwerking | F40: automatische regeling | G40: 1 | H40: …ogelijk en bepalen waarschuwingsdrempels en criteria om processen voor respons op ICT-gerelateerde incidenten in werking te stellen, met inbegrip van automatische waarschuwingsmechanismen voor de betrokken personeelsleden die belast zijn met de respons op ICT-gerelateerde incidenten. | L40: 32022R2554:10:2:8
A41: 40 | B41: adviezen | D41: advies (EU) | G41: 3 | H41: …r reële omstandigheden als bedoeld in de artikelen 57, 59 en 60; e) op verzoek van de Commissie of op eigen initiatief aanbevelingen en schriftelijke adviezen uitbrengen over alle relevante aangelegenheden in verband met de uitvoering van deze verordening en de consistente en doeltreffende toepassing ervan,… | L41: 32024R1689:66:whole:17
A42: 41 | B42: uittreksels | C42: voor eensluidend gewaarmerkte kopieën of uittreksels | D42: uitlevering | E42: ontvoering | F42: uitverkoop | G42: 1 | H42: …procedures en alle overig voor de uitvoering van zijn taken relevant materiaal te onderzoeken, ongeacht de drager waarop dit materiaal opgeslagen; b) voor eensluidend gewaarmerkte kopieën of uittreksels te maken of te verkrijgen van deze registers, data, gedocumenteerde procedures en enig ander materiaal; c) vertegenwoordigers van kritieke derde aanb… | L42: 32022R2554:38:2:3
A43: 42 | B43: persoonsgegevens van een abonnee | D43: gegevensbescherming | E43: persoonlijke gegevens | F43: recht op privacy | G43: 1 | H43: In een algemeen beschikbare abonneelijst en in het voor een abonnee-informatiedienst gebruikte abonneebestand worden uitsluitend persoonsgegevens van een abonnee opgenomen, indien de abonnee daarvoor toestemming heeft verleend en blijft deze beperkt tot de door hem daarbij aangegeven persoonsgegevens. Aan het … | L43: BWBR0009950:11.6:2:5
A44: 43 | B44: afspraken | D44: communicatie | E44: afspraak tussen ondernemingen | F44: besluit | G44: 12 | H44: … streven naar overeenstemming over de omstandigheden en voorwaarden waaronder coördinatie van de civiele werken plaatsvindt. Zij maken in ieder geval afspraken over: a. de plaats, het tijdstip en de wijze van uitvoering van de werkzaamheden, b. een redelijke vergoeding van de kosten die zijn gemoeid met coör… | L44: BWBR0009950:5a.11:2:3
A45: 44 | B45: verslag | D45: verslag | G45: 37 | H45: [1] EU 32024R1689:99:11:15: De lidstaten brengen jaarlijks verslag uit aan de Commissie over de administratieve geldboeten die zij in de loop van dat jaar overeenkomstig dit artikel hebben opgelegd, en over alle daar… [2] NL BWBR0052872:94:1:1: Onze Minister zendt binnen achttien maanden na de inwerkingtreding van deze wet aan de Staten-Generaal een verslag waarin de resultaten van een invoeringstoets over de uitvoerbaarheid, de handhaafbaarheid, de regeldruk, de samenloop en de werkbaarheid van deze wet in de praktijk zijn opgenomen. [3] EU 32024R1689:56:5:12: Het AI-bureau streeft ernaar ervoor te zorgen dat de deelnemers aan de praktijkcodes regelmatig verslag uitbrengen aan het AI-bureau over de uitvoering van de verbintenissen en de genomen maatregelen en de resultaten daarvan, onder meer waar nodig gemet… | L45: 32024R1689:99:11:15, BWBR0052872:94:1:1, 32024R1689:56:5:12
A46: 45 | B46: aanbieder | C46: de betreffende aanbieder | D46: provider | G46: 5 | H46: … elektronisch communicatienetwerk, een openbare elektronische communicatiedienst of bijbehorende faciliteiten, stelt de Autoriteit Consument en Markt de betreffende aanbieder daarvan op de hoogte. | L46: BWBR0009950:18.20:3:3
A47: 46 | B47: risicobeoordeling van het incident en corrigerende maatregelen | C47: een risicobeoordeling van het incident en corrigerende maatregelen | D47: risicobeheer | G47: 1 | H47: … op grond van lid 1 verricht de aanbieder onverwijld het nodige onderzoek in verband met het ernstige incident en het betrokken AI-systeem. Dit omvat een risicobeoordeling van het incident en corrigerende maatregelen. De aanbieder werkt tijdens het in de eerste alinea genoemde onderzoek samen met de bevoegde autoriteiten en, in voorkomend geval, met de betrokken a… | L47: 32024R1689:73:6:8
A48: 47 | B48: advies | D48: advies (EU) | G48: 29 | H48: [1] EU 32016R0679:57:1:5: …werking. Bijzondere aandacht wordt besteed aan specifiek op kinderen gerichte activiteiten; c) zij verleent overeenkomstig het recht van de lidstaat, advies aan het nationale parlement, de regering, en andere instellingen en organen over wetgevingsinitiatieven en bestuursmaatregelen in verband met de besc… [2] NL BWBR0048156:11:7:8: …het Bureau bevordering integriteitsbeoordelingen, bedoeld in artikel 8 van de Wet bevordering integriteitsbeoordelingen door het openbaar bestuur, om een advies als bedoeld in artikel 9 van die wet worden gevraagd. [3] EU 32016R0679:64:1:1: Het Comité brengt een advies uit wanneer een bevoegde toezichthoudende autoriteit voornemens is een van onderstaande maatregelen vast te stellen. Hiertoe deelt de bevoegde toezic… | L48: 32016R0679:57:1:5, BWBR0048156:11:7:8, 32016R0679:64:1:1
A49: 48 | B49: bevoegdheden | D49: administratieve bevoegdheid | E49: institutionele bevoegdheid | F49: regelgevende bevoegdheid | G49: 24 | H49: [1] EU 32022R2554:39:2:4: …zegelen zolang en voor zover dit nodig is voor de inspectie. De functionarissen en andere personen die door de lead overseer zijn gemachtigd, oefenen deze bevoegdheden uit na overlegging van een schriftelijke machtiging waarin het onderwerp en het doel van de inspectie worden vermeld, alsmede de dwangsommen als bedo… [2] NL BWBR0009950:15.3d:3:3: De ambtenaren, bedoeld in het eerste lid, beschikken voor de uitvoering van een gezamenlijk onderzoek over de bevoegdheden waarover zij ook voor het verlenen van bijstand beschikken. Artikel 15.3b, derde lid, is van overeenkomstige toepassing. [3] EU 32024R1689:74:5:4: … krachtens artikel 14 van Verordening (EU) 2019/1020 kunnen markttoezichtautoriteiten met het oog op de doeltreffende handhaving van deze verordening de in artikel 14, lid 4, punten d) en j), van die verordening bedoelde bevoegdheden naargelang van het geval op afstand uitoefenen. | L49: 32022R2554:39:2:4, BWBR0009950:15.3d:3:3, 32024R1689:74:5:4
A50: 49 | B50: pseudonimisering | C50: pseudonimisering als bedoeld in artikel 4, onderdeel 5, van de verordening | D50: anonimisering | G50: 2 | H50: … Burgerlijk Wetboek rust dan wel heeft gerust, wordt voor aanvang van de verwerking van persoonsgegevens voor de opdracht, bedoeld in het eerste lid, pseudonimisering als bedoeld in artikel 4, onderdeel 5, van de verordening toegepast en vervolgens onafgebroken gecontinueerd. | L50: BWBR0040940:23a:2:2
A51: 50 | B51: of aan de toezichtvoorwaarden voor het sluiten van het contract is voldaan | D51: afsluiten van een contract | E51: bevoegdheid om overeenkomsten te sluiten | F51: verbreken van een contract | G51: 1 | H51: …de contractuele overeenkomst betrekking heeft op het gebruik van ICT-diensten die een kritieke of belangrijke functie ondersteunen; b) beoordelen zij of aan de toezichtvoorwaarden voor het sluiten van het contract is voldaan; c) identificeren en beoordelen zij alle relevante risico’s met betrekking tot de contractuele overeenkomst, met inbegrip van de mogelijkheid dat dez… | L51: 32022R2554:28:4:14
A52: 51 | B52: kennis | C52: over kennis en vaardigheden | D52: kennisbeheer | E52: digitale kennis | F52: informatie | G52: 2 | H52: Ieder lid van het bestuur van een essentiële entiteit of belangrijke entiteit beschikt over kennis en vaardigheden om: a. risico’s voor de beveiliging van netwerk- en informatiesystemen te kunnen identificeren; b. risicobeheersmaatregelen op het gebied van cyberbe… | L52: BWBR0052872:24:2:2
A53: 52 | B53: nummer | C53: de toekenning van een nummer | D53: telefoon | E53: numerieke besturing | F53: informatie | G53: 12 | H53: …ene maatregel van bestuur wordt bepaald welke gedragingen van een nummergebruiker voor de Autoriteit Consument en Markt aanleiding kunnen zijn om: a. de toekenning van een nummer te weigeren, op te schorten of in te trekken, b. de aanbieder van een openbare elektronische communicatiedienst een aanwijzing te geven de betaling d… | L53: BWBR0009950:4.4:1:3
A54: 53 | B54: wijze de mededeling wordt gedaan | C54: op welke wijze de mededeling wordt gedaan | D54: mededeling van de regering | E54: mededeling aan de pers | F54: medeëigendom | G54: 1 | H54: De Autoriteit Consument en Markt stelt vast op welke wijze de mededeling wordt gedaan en doet daarvan mededeling in de Staatscourant. | L54: BWBR0009950:2.1:3:4
A55: 54 | B55: vertegenwoordigers van de financiële entiteit | D55: politieke vertegenwoordiging | E55: vertegenwoordiger van lokale of regionale autoriteit | F55: financiële deelneming | G55: 1 | H55: …iervan te ontvangen of te maken; b) inspecties of onderzoeken ter plaatse uit te voeren, met inbegrip van, maar niet beperkt tot: i) het oproepen van vertegenwoordigers van de financiële entiteit en hen verzoeken om mondelinge of schriftelijke toelichting te geven bij feiten of documenten met betrekking tot het onderwerp en het doel van het on… | L55: 32022R2554:50:2:5
A56: 55 | B56: kennelijk ongegronde of buitensporige aard van het verzoek | C56: de kennelijk ongegronde of buitensporige aard van het verzoek | D56: beroep tot nietigverklaring | E56: beroep wegens nalatigheid | F56: beroep wegens niet-nakomen | G56: 2 | H56: …administratieve kosten een redelijke vergoeding aanrekenen, of weigeren aan het verzoek gevolg te geven. Het is aan de toezichthoudende autoriteit om de kennelijk ongegronde of buitensporige aard van het verzoek aan te tonen. | L56: 32016R0679:57:4:37
A57: 56 | B57: kritieke derde aanbieder van ICT-diensten | C57: de kritieke derde aanbieder van ICT-diensten | D57: provider | G57: 3 | H57: …n constateren dat een kritieke derde aanbieder van ICT-diensten zich verzet tegen een krachtens dit artikel gelaste inspectie, stelt de lead overseer de kritieke derde aanbieder van ICT-diensten in kennis van de gevolgen van dit verzet, met inbegrip van de mogelijkheid voor de bevoegde autoriteiten van de financiële entiteit om van de financi… | L57: 32022R2554:39:7:11
A58: 57 | B58: billijke en niet-discriminerende eisen | C58: billijke en niet-discriminerende eisen en voorwaarden | D58: niet rechtsbevoegd zijn | G58: 1 | H58: …riteit Consument en Markt kan bij de beslechting van een geschil inzake de nakoming van een bij of krachtens hoofdstuk 5a of 5c gestelde verplichting billijke en niet-discriminerende eisen en voorwaarden stellen aan de bij dat geschil betrokken partijen, het medegebruik of de coördinatie. | L58: BWBR0009950:12.4:1:1
A59: 58 | B59: automatische oproep- en communicatiesystemen zonder menselijke tussenkomst, faxen en elektronische berichten | C59: Het gebruik van automatische oproep- en communicatiesystemen zonder menselijke tussenkomst, faxen en elektronische berichten | D59: ongevraagde elektronische communicatie | E59: geautomatiseerd informatiesysteem | F59: computersystemen | G59: 1 | H59: Het gebruik van automatische oproep- en communicatiesystemen zonder menselijke tussenkomst, faxen en elektronische berichten voor het overbrengen van ongevraagde communicatie voor commerciële, ideële of charitatieve doeleinden is verboden, tenzij de verzender kan aantonen d… | L59: BWBR0009950:11.7:1:1
A60: 59 | B60: of de maatregel gerechtvaardigd is | D60: aanbeveling van de Raad | E60: kiesgerechtigd zijn | F60: uitvoeringsbesluit van de Raad | G60: 1 | H60: …et de betrokken lidstaten en de betrokken operators en evalueert de genomen nationale maatregelen. Aan de hand van die evaluatie besluit de Commissie of de maatregel gerechtvaardigd is, en stelt zij zo nodig andere passende maatregelen voor. | L60: 32024R1689:82:4:5
A61: 60 | B61: passende en evenredige technische, operationele en organisatorische maatregelen | D61: Verdrag inzake stabiliteit, coördinatie en bestuur | E61: Programma voor gezonde en resultaatgerichte regelgeving | F61: Autoriteit voor paraatheid en respons inzake noodsituaties op gezondheidsgebied | G61: 3 | H61: De lidstaten zorgen ervoor dat essentiële en belangrijke entiteiten passende en evenredige technische, operationele en organisatorische maatregelen nemen om de risico’s voor de beveiliging van de netwerk- en informatiesystemen die deze entiteiten voor hun werkzaamheden of voor het verlenen van hu… | L61: 32022L2555:21:1:2
A62: 61 | B62: derde aanbieder van ICT-diensten | C62: naar een andere derde aanbieder van ICT-diensten of naar interne oplossingen | D62: provider | G62: 4 | H62: …inanciële entiteit te beperken of voor een doeltreffende afwikkeling en herstructurering te zorgen; ii) waarin de financiële entiteit kan overstappen naar een andere derde aanbieder van ICT-diensten of naar interne oplossingen in overeenstemming met de complexiteit van de geleverde dienst. In afwijking van punt e) kunnen de derde aanbieder van ICT-diensten en de financiële … | L62: 32022R2554:30:3:15
A63: 62 | B63: ontheffing | D63: ontvoering | E63: onteigening | F63: uitlevering | G63: 7 | H63: …penbaar elektronisch communicatienetwerk en een aanbieder van een openbare elektronische communicatiedienst kan door de Autoriteit Consument en Markt ontheffing worden verleend van de verplichtingen die voortvloeien uit de artikelen 11.4, eerste lid, onderdeel b, en 11.9 tot en met 11.11. | L63: BWBR0009950:11.12:1:1
A64: 63 | B64: opgelegde verplichting | C64: de opgelegde verplichting | D64: contract | G64: 6 | H64: …lichting is opgelegd als bedoeld in het eerste, derde of vijfde lid, beoordeelt de Autoriteit Consument en Markt de resultaten daarvan en besluit zij de opgelegde verplichting in stand te houden, in te trekken of te wijzigen. | L64: BWBR0009950:6.3:9:16
A65: 64 | B65: vergoeding | C65: een vergoeding | D65: vergoeding | G65: 7 | H65: Indien de Autoriteit en Consument een vergoeding vaststelt voor het medegebruik van fysieke infrastructuur, wordt ervoor gezorgd dat de netwerkexploitant een eerlijke kans heeft om zijn kosten terug… | L65: BWBR0009950:12.4:2:3
A66: 65 | B66: last onder bestuursdwang | C66: een last onder bestuursdwang | D66: openbaarheid van het bestuur | E66: departementaal bestuur | F66: misbruik van bevoegdheid | G66: 8 | H66: … lid, laatste twee volzinnen, 18, eerste en vierde lid, 19, 21, tweede, derde, vierde en vijfde lid, en 22, tweede lid, bevoegd tot oplegging van: a. een last onder bestuursdwang; of b. een bestuurlijke boete van ten hoogste het bedrag, genoemd in artikel 40, vierde lid, van de dataverordening. | L66: BWBR0051796:8:2:3
A67: 66 | B67: erkenning | C67: een erkenning | D67: bekendmaking | E67: beginsel van wederzijdse erkenning | F67: schenking | G67: 9 | H67: Onze Minister kan een erkenning wijzigen, schorsen of intrekken indien niet wordt voldaan aan de eisen bedoeld in het tweede of derde lid, de eisen, voorschriften of beperkingen bed… | L67: BWBR0048156:9:7:13
A68: 67 | B68: Commissie | D68: conferentie | E68: comitologie | F68: delegatie van de Commissie | G68: 19 | H68: [1] EU 32024R1689:46:3:9: …kttoezichtautoriteit concludeert dat het AI-systeem met een hoog risico aan de voorschriften van afdeling 2 voldoet. De markttoezichtautoriteit stelt de Commissie en de andere lidstaten in kennis van op grond van de leden 1 en 2 verstrekte toelatingen. Deze verplichting geldt niet voor gevoelige operationele gegevens met betrekking t… [2] EU 32024R1689:66:whole:16: De AI-board adviseert en assisteert de Commissie en de lidstaten teneinde de consistente en doeltreffende toepassing van deze verordening te vergemakkelijken. Daartoe kan de AI-board met name: a) bi… [3] EU 32024R1689:66:whole:4: De AI-board adviseert en assisteert de Commissie en de lidstaten teneinde de consistente en doeltreffende toepassing van deze verordening te vergemakkelijken. Daartoe kan de AI-board met name: a) bi… | L68: 32024R1689:46:3:9, 32024R1689:66:whole:16, 32024R1689:66:whole:4
A69: 68 | B69: attributen | C69: alle op grond van artikel 12 aangewezen attributen | D69: etiketteren | E69: profielen | G69: 1 | H69: …chtigd is namens de onderneming of rechtspersoon, bedoeld in artikel 15, eerste lid, op te treden bij de toegang tot elektronische dienstverlening en alle op grond van artikel 12 aangewezen attributen. | L69: BWBR0048156:13:2:7
A70: 69 | B70: risico van belangenconflicten met betrekking tot de aangewezen cyberbeveiligingsdeskundigen | C70: elk risico van belangenconflicten met betrekking tot de aangewezen cyberbeveiligingsdeskundigen | D70: cyberveiligheid | E70: weerbaarheid op het gebied van cyberbeveiliging | G70: 1 | H70: De lidstaten zorgen ervoor dat elk risico van belangenconflicten met betrekking tot de aangewezen cyberbeveiligingsdeskundigen aan de andere lidstaten, de samenwerkingsgroep, de Commissie en Enisa wordt gemeld voordat met de collegiale toetsing wordt begonnen. De aan een coll… | L70: 32022L2555:19:8:20
A71: 70 | B71: toezichthoudende autoriteit | C71: de toezichthoudende autoriteit | D71: administratief toezicht | E71: bevoegde nationale autoriteit | F71: toezicht op de onderneming | G71: 5 | H71: Wanneer er in een lidstaat meer dan één toezichthoudende autoriteit is gevestigd, wijst die lidstaat de toezichthoudende autoriteit aan die die autoriteiten in het Comité moet vertegenwoordigen en stelt hij de procedure vast om ervoor te zorgen dat de andere autoriteiten de regels… | L71: 32016R0679:51:3:4
A72: 71 | B72: Persoonsgegevens | D72: persoonlijke gegevens | E72: publieke gegevens | F72: invoer van gegevens | G72: 6 | H72: Persoonsgegevens moeten: a) worden verwerkt op een wijze die ten aanzien van de betrokkene rechtmatig, behoorlijk en transparant is („rechtmatigheid, behoorlijkheid e… | L72: 32016R0679:5:1:4
A73: 72 | B73: besluit over de geschilbeslechting | C73: het besluit over de geschilbeslechting | D73: besluit | E73: besluit (EU) | G73: 2 | H73: In afwijking van het tweede lid kan de Autoriteit Consument en Markt in uitzonderlijke omstandigheden ambtshalve of op verzoek van partijen voorlopige maatregelen nemen, indien er een dringende noodzaak is om te handelen teneinde de mededinging of de belangen van eindgebruikers te beschermen. | L73: BWBR0009950:12.8:3:4
A74: 73 | B74: vergoeding | C74: de vergoeding | D74: vergoeding | G74: 7 | H74: Indien het bod op de in artikel 9.3, zesde lid, onderdeel b, bedoelde wijze is uitgebracht, bestaat de vergoeding uit het bod, uitgebracht door degene die op grond van artikel 9.3, achtste of negende lid, is aangewezen als universeledienstverlener, vermenigvuldig… | L74: BWBR0009950:9.4:2:2
A75: 74 | B75: binnen het toepassingsgebied vallende entiteiten en, indien van toepassing, andere entiteiten, op vrijwillige basis onderling relevante informatie over cyberbeveiliging kunnen uitwisselen, met inbegrip van informatie over cyberdreigingen, bijna-incidenten, kwetsbaarheden, technieken en procedures, indicatoren voor aantasting, vijandige tactieken, dreigingsactorspecifieke informatie, cyberbeveiligingswaarschuwingen en aanbevelingen betreffende de configuratie van cyberbeveiligingsinstrumenten om cyberaanvallen te detecteren | C75: binnen het toepassingsgebied van deze richtlijn vallende entiteiten en, indien van toepassing, andere entiteiten die niet binnen het toepassingsgebied van deze richtlijn vallen, op vrijwillige basis onderling relevante informatie over cyberbeveiliging kunnen uitwisselen, met inbegrip van informatie over cyberdreigingen, bijna-incidenten, kwetsbaarheden, technieken en procedures, indicatoren voor aantasting, vijandige tactieken, dreigingsactorspecifieke informatie, cyberbeveiligingswaarschuwingen en aanbevelingen betreffende de configuratie van cyberbeveiligingsinstrumenten om cyberaanvallen te detecteren | D75: gebied | G75: 1 | H75: De lidstaten zorgen ervoor dat binnen het toepassingsgebied van deze richtlijn vallende entiteiten en, indien van toepassing, andere entiteiten die niet binnen het toepassingsgebied van deze richtlijn vallen, op vrijwillige basis onderling relevante informatie over cyberbeveiliging kunnen uitwisselen, met inbegrip van informatie over cyberdreigingen, bijna-incidenten, kwetsbaarheden, technieken en procedures, indicatoren voor aantasting, vijandige tactieken, dreigingsactorspecifieke informatie, cyberbeveiligingswaarschuwingen en aanbevelingen betreffende de configuratie van cyberbeveiligingsinstrumenten om cyberaanvallen te detecteren, wanneer dat uitwisselen van informatie: a) beoogt incidenten te voorkomen, te detecteren, erop te reageren of ervan te herstellen of de gevolgen erv… | L75: 32022L2555:29:1:1
A76: 75 | B76: door andere toezichthoudende autoriteiten gevraagde informatie | C76: de door andere toezichthoudende autoriteiten gevraagde informatie | D76: raadpleging van informatie | E76: informatie van de publieke sector | F76: oproepen van gegevens | G76: 1 | H76: Toezichthoudende autoriteiten tot wie het verzoek is gericht delen in de regel de door andere toezichthoudende autoriteiten gevraagde informatie langs elektronische weg mee door middel van een standaardformulier. | L76: 32016R0679:61:6:12
A77: 76 | B77: gemachtigde | C77: een gemachtigde | D77: beschuldigde | E77: gedetineerde | F77: boetvaardige | G77: 7 | H77: …e landen zijn gevestigd, wijzen voordat zij hun AI-systemen met een hoog risico in de Unie in de handel brengen, middels een schriftelijke machtiging een gemachtigde aan die is gevestigd in de Unie. | L77: 32024R1689:22:1:1
A78: 77 | B78: overige taken | D78: opname | E78: bewarend beslag | G78: 1 | H78: …aatsen van een publiek identificatiemiddel op betrouwbaarheidsniveau hoog op het rijbewijs. Aan de Dienst Wegverkeer kunnen bij ministeriële regeling overige taken worden opgedragen die samenhangen met het plaatsen van een publiek identificatiemiddel op het rijbewijs. | L78: BWBR0048156:5:4:5
A79: 78 | B79: gegevens | D79: persoonlijke gegevens | E79: informatie | F79: gegevensmateriaal | G79: 44 | H79: [1] EU 32022R2554:30:2:8: …de locaties, met name de regio’s of landen, waar de contractueel overeengekomen of uitbestede functies en ICT-diensten moeten worden geleverd en waar gegevens moeten worden verwerkt, met inbegrip van de opslaglocatie, en de verplichting voor de derde aanbieder van ICT-diensten om de financiële entiteit voor… [2] NL BWBR0009950:18.3a:whole:1: Andere bestuursorganen dan de Autoriteit Consument en Markt zijn bevoegd uit eigen beweging en verplicht desgevraagd Onze Minister de gegevens te verstrekken die noodzakelijk zijn voor de uitvoering en het toezicht op de naleving van deze wet of van de eidas-verordening door Onze Minister. [3] EU 32016R0679:30:1:2: …de verwerkingsverantwoordelijke houdt een register van de verwerkingsactiviteiten die onder hun verantwoordelijkheid plaatsvinden. Dat register bevat alle volgende gegevens: a) de naam en de contactgegevens van de verwerkingsverantwoordelijke en eventuele gezamenlijke verwerkingsverantwoordelijken, en, in voorkomend geva… | L79: 32022R2554:30:2:8, BWBR0009950:18.3a:whole:1, 32016R0679:30:1:2
A80: 79 | B80: financiële entiteit | C80: een financiële entiteit ertoe | D80: financiële audit | E80: financiële technologie | F80: financiële behoefte | G80: 4 | H80: …t de in de aanbevelingen aan de kritieke derde aanbieder van ICT-diensten geconstateerde risico’s zijn verholpen. Indien nodig kunnen de autoriteiten een financiële entiteit ertoe verplichten de contractuele overeenkomsten met de kritieke derde aanbieder van ICT-diensten geheel of gedeeltelijk te beëindigen. | L80: 32022R2554:42:6:16
A81: 80 | B81: voldoende middelen | D81: behoefte aan kapitaal | E81: aangevulde realiteit | F81: geavanceerd materiaal | G81: 8 | H81: De lidstaten zorgen ervoor dat de in de leden 1 en 2 bedoelde bevoegde autoriteiten voldoende middelen toewijzen om doeltreffend en tijdig aan dit artikel te voldoen. In voorkomend geval werken de nationale bevoegde autoriteiten samen met andere releva… | L81: 32024R1689:57:4:9
A82: 81 | B82: secretariaat van de AI-board | C82: het secretariaat van de AI-board | D82: secretariaat van de instelling | E82: secretariaatspersoneel | G82: 1 | H82: De AI-board wordt voorgezeten door een van de vertegenwoordigers van de lidstaten. Het AI-bureau verzorgt het secretariaat van de AI-board, roept op verzoek van de voorzitter de vergaderingen bijeen en stelt de agenda op overeenkomstig de taken van de AI-board krachtens deze verordening … | L82: 32024R1689:65:8:20
A83: 82 | B83: beperkingen | C83: nadere verplichtingen en beperkingen | D83: beperking van bewegingsvrijheid | E83: verplichting | F83: beroepsverbod | G83: 13 | H83: …edoelde aanbieders in het belang van de bescherming van persoonsgegevens en de bescherming van de persoonlijke levenssfeer van abonnees en gebruikers nadere verplichtingen en beperkingen worden opgelegd ten behoeve van de veiligheid en beveiliging van de door hen aangeboden netwerken en diensten. | L83: BWBR0009950:11.3:4:7
A84: 83 | B84: regels | D84: reglement | G84: 92 | H84: [1] EU 32016R0679:83:7:8: …d de bevoegdheden tot het nemen van corrigerende maatregelen van de toezichthoudende autoriteiten overeenkomstig artikel 58, lid 2, kan elke lidstaat regels vaststellen betreffende de vraag of en in hoeverre administratieve geldboeten kunnen worden opgelegd aan in die lidstaat gevestigde overheidsinstanti… [2] NL BWBR0009950:18.13:1:1: Onverminderd het overigens bij of krachtens deze wet bepaalde worden de bij of krachtens deze wet te nemen maatregelen en regels genomen met inachtneming van het belang van de bescherming van persoonsgegevens en de bescherming van de persoonlijke levenssfeer alsmede de bescherm… [3] EU 32016R0679:61:7:14: …iten tot wie een verzoek is gericht nemen uit hoofde van een verzoek om wederzijdse bijstand, zijn kosteloos. De toezichthoudende autoriteiten kunnen regels overeenkomen om elkaar te vergoeden voor specifieke uitgaven die voortvloeien uit het verstrekken van wederzijdse bijstand in uitzonderlijke omstandi… | L84: 32016R0679:83:7:8, BWBR0009950:18.13:1:1, 32016R0679:61:7:14
A85: 84 | B85: transparantieverplichtingen | C85: de transparantieverplichtingen van dit lid | D85: contract | G85: 1 | H85: …zoeken of te vervolgen. Wanneer de content deel uitmaakt van een kennelijk artistiek, creatief, satirisch, fictief of analoog werk of programma, zijn de transparantieverplichtingen van dit lid beperkt tot de openbaarmaking van het bestaan van dergelijke gegenereerde of bewerkte content op een passende wijze die de weergave of het genot van … | L85: 32024R1689:50:4:13
A86: 85 | B86: schade | C86: de voorlopige effecten, schade en verliezen | D86: schade | G86: 5 | H86: …incident en waarmee verdere schade kan worden voorkomen, alsmede op maat gesneden respons- en herstelprocedures in overeenstemming met artikel 12; d) de voorlopige effecten, schade en verliezen te ramen; e) maatregelen voor communicatie en crisisbeheersing op te stellen die garanderen dat aan alle betrokken interne personeelsleden en externe… | L86: 32022R2554:11:2:6
A87: 86 | B87: kosten | C87: alle kosten die voortvloeien uit de uitvoering van de in deze afdeling opgenomen taken | D87: proceskosten | E87: administratieve kosten | F87: vergoeding | G87: 8 | H87: …ken van directe oversightactiviteiten. Het bedrag van de vergoeding die de kritieke derde aanbieder van ICT-diensten in rekening wordt gebracht, dekt alle kosten die voortvloeien uit de uitvoering van de in deze afdeling opgenomen taken, en staat in verhouding tot diens omzet. | L87: 32022R2554:43:1:2
A88: 87 | B88: vertrouwelijke informatie | D88: vertrouwelijkheid | G88: 1 | H88: De Commissie en de lidstaten kunnen zo nodig en met inachtneming van de relevante bepalingen van internationale overeenkomsten en handelsakkoorden vertrouwelijke informatie uitwisselen met regelgevingsinstanties van derde landen waarmee zij bilaterale of multilaterale vertrouwelijkheidsovereenkomsten hebben gesloten die … | L88: 32024R1689:78:5:12
A89: 88 | B89: besluit | D89: besluit | E89: besluit (EU) | G89: 49 | H89: [1] EU 32016R0679:65:2:3: Het in lid 1 bedoelde besluit wordt binnen één maand na de verwijzing van de aangelegenheid vastgesteld met een tweederdemeerderheid van de leden van het Comité. Deze termijn kan … [2] NL BWBR0009950:12.2:7:10: Op aanvraag van de gezamenlijke nummerhouders kan de Autoriteit Consument en Markt een besluit als bedoeld in het zesde lid intrekken. [3] EU 32016R0679:60:8:18: Ingeval een klacht is afgewezen of verworpen, stelt de toezichthoudende autoriteit waarbij de klacht is ingediend, in afwijking van lid 7, het besluit vast en deelt zij het mee aan de klager en stelt zij de verwerkingsverantwoordelijke ervan in kennis. | L89: 32016R0679:65:2:3, BWBR0009950:12.2:7:10, 32016R0679:60:8:18
A90: 89 | B90: beëindiging van de status gekwalificeerd | C90: tot beëindiging van de status gekwalificeerd | D90: status van de verkozen persoon | E90: verjaring van de vordering | G90: 1 | H90: Onze Minister kan onverminderd artikel 20, derde lid, van de eidas-verordening, tot beëindiging van de status gekwalificeerd overgaan: a. indien een gekwalificeerde verlener van vertrouwensdiensten in strijd met het bepaalde bij of krachtens deze wet handelt ten aanzien van… | L90: BWBR0009950:2.5d:1:1
A91: 90 | B91: verwerking van verkeersgegevens | C91: De verwerking van verkeersgegevens | D91: gegevensverwerking | E91: opslag van gegevens | F91: informatieverwerking | G91: 1 | H91: De verwerking van verkeersgegevens in overeenstemming met het eerste tot en met vierde lid mag alleen geschieden door personen die werkzaam zijn onder het gezag van de aanbieder voor f… | L91: BWBR0009950:11.5:5:9
A92: 91 | B92: verslag over haar bevindingen | C92: een verslag over haar bevindingen | D92: verslag | G92: 1 | H92: …aangemelde instantie afgegeven certificaten; b) dient de aanmeldende autoriteit binnen drie maanden na mededeling van de wijzigingen in de aanwijzing een verslag over haar bevindingen in bij de Commissie en de overige lidstaten; c) schrijft de aanmeldende autoriteit voor dat de aangemelde instantie binnen een redelijke, door de aut… | L92: 32024R1689:36:7:19
A93: 92 | B93: kwetsbaarheden | C93: cyberdreigingen, kwetsbaarheden en incidenten | D93: onverkiesbaarheid | E93: handelingsbekwaamheid | F93: meeteenheid | G93: 3 | H93: Het CSIRT heeft de volgende taken: a. het monitoren en analyseren van cyberdreigingen, kwetsbaarheden en incidenten op nationaal niveau, en het op verzoek verlenen van bijstand aan de betrokken essentiële entiteit of belangrijke entiteit met betrekking tot het real… | L93: BWBR0052872:16:2:3
A94: 93 | B94: administratieve geldboeten | D94: geldboete | G94: 11 | H94: De Europese Toezichthouder voor gegevensbescherming kan administratieve geldboeten opleggen aan instellingen, organen en instanties van de Unie die binnen het toepassingsgebied van deze verordening vallen. Bij het besluiten om al da… | L94: 32024R1689:100:1:1
A95: 94 | B95: verbod op het houden of verkrijgen van overwegende zeggenschap | C95: een verbod op het houden of verkrijgen van overwegende zeggenschap | D95: verordenende bevoegdheid | E95: bevoegdheid van de uitvoerende macht | F95: beperking van de verblijfsvergunning | G95: 1 | H95: Indien een verbod op het houden of verkrijgen van overwegende zeggenschap niet volgt op een melding op grond van artikel 14a.2, wordt een verbod opgelegd binnen acht maanden nadat de feiten of omstandigheden op grond waarva… | L95: BWBR0009950:14a.4:5:5
A96: 95 | B96: dwangsom | C96: De in lid 6 bedoelde dwangsom | D96: dwangsom | G96: 3 | H96: De in lid 6 bedoelde dwangsom wordt dagelijks opgelegd tot aan de verplichtingen is voldaan, gedurende een termijn van ten hoogste zes maanden volgend op de kennisgeving van het b… | L96: 32022R2554:35:7:21
A97: 96 | B97: voorschrift | C97: het voorschrift | D97: verordening | G97: 2 | H97: Onverminderd het eerste lid kan aan een vergunning het voorschrift worden verbonden dat de frequentieruimte waarop de vergunning betrekking heeft moet worden gebruikt voor de toepassing van bij de vergunning aan te w… | L97: BWBR0009950:3.14:4:6
A98: 97 | B98: bestuurlijke boete | D98: administratieve boete | E98: geldboete | F98: bestuurlijke verantwoordelijkheid | G98: 18 | H98: [1] NL BWBR0052872:93:1:1: De bevoegde autoriteit kan een lid van het bestuur van een essentiële entiteit of belangrijke entiteit een bestuurlijke boete opleggen in geval van: a. overtreding van het bepaalde bij of krachtens artikel 24, tweede tot en met zesde lid; b. overtreding van artikel 5:20, eer… [2] NL BWBR0052872:58:3:4: … persoonsgegevens dan wel de bevoegde toezichthoudende autoriteiten, bedoeld in de artikelen 55 en 56 van de Algemene verordening gegevensbescherming een bestuurlijke boete opleggen op grond van artikel 58, tweede lid, onderdeel i, van de Algemene verordening gegevensbescherming, legt de bevoegde autoriteit geen bestuurl… [3] NL BWBR0009950:15.4:2:2: …an ingeval van overtreding van een wettelijk voorschrift met het toezicht op de naleving waarvan zij het ingevolge artikel 15.1, derde lid, is belast een bestuurlijke boete opleggen van ten hoogste € 900.000, of, indien dat meer is, 1% van de omzet van de onderneming. | L98: BWBR0052872:93:1:1, BWBR0052872:58:3:4, BWBR0009950:15.4:2:2
A99: 98 | B99: bevoegdheid | C99: de bevoegdheid | D99: administratieve bevoegdheid | E99: institutionele bevoegdheid | F99: verordenende bevoegdheid | G99: 10 | H99: Overeenkomstig artikel 75 verlenen de lidstaten hun markttoezichtautoriteiten de bevoegdheid om aanbieders en potentiële aanbieders te verplichten informatie te verstrekken, om onaangekondigde inspecties op afstand of ter plaatse uit te voere… | L99: 32024R1689:60:6:28
A100: 99 | B100: natuurlijke personen | C100: alle andere natuurlijke personen of rechtspersonen | D100: natuurlijke persoon | G100: 2 | H100: …g te geven bij feiten of documenten met betrekking tot het onderwerp en het doel van het onderzoek, en de antwoorden op te tekenen; ii) het horen van alle andere natuurlijke personen of rechtspersonen die daarin toestemmen, teneinde informatie over het onderwerp van een onderzoek te verzamelen; c) corrigerende maatregelen te eisen voor inbreuken op… | L100: 32022R2554:50:2:8
...

Sheet key
A1: row | B1: kind | C1: stratum | D1: source | E1: level | F1: conf_1 | G1: pct_1 | H1: w_EU | I1: w_NL | J1: text
A2: 1 | B2: sample | C2: EU | emb low (p20-47) | D2: EU | E2: embedding | F2: 0.2776 | G2: 40.7 | J2: verhouding tot het ICT-risico van de financiële entiteit
A3: 2 | B3: census | C3: census | D3: EU+NL | E3: phrase | F3: 1 | H3: 4 | I3: 23 | J3: verplichtingen
A4: 3 | B4: sample | C4: NL | emb high (p73-100) | D4: NL | E4: embedding | F4: 0.4735 | G4: 92.9 | J4: misbruik
A5: 4 | B5: census | C5: census | D5: EU+NL | E5: phrase | F5: 1 | H5: 62 | I5: 25 | J5: informatie
A6: 5 | B6: sample | C6: NL | emb mid (p47-73) | D6: NL | E6: embedding | F6: 0.3806 | G6: 68.2 | J6: nummergebruiker
A7: 6 | B7: sample | C7: NL | emb low (p20-47) | D7: NL | E7: embedding | F7: 0.2621 | G7: 36.6 | J7: Archiefbescheiden van de Autoriteit Consument en Markt
A8: 7 | B8: census | C8: census | D8: EU+NL | E8: embedding | F8: 0.4231 | G8: 79.5 | H8: 10 | I8: 13 | J8: termijn
A9: 8 | B9: census | C9: census | D9: EU+NL | E9: embedding | F9: 0.2295 | G9: 27.9 | H9: 1 | I9: 53 | J9: nadere regels
A10: 9 | B10: sample | C10: NL | emb mid (p47-73) | D10: NL | E10: embedding | F10: 0.3393 | G10: 57.1 | J10: beperkingen
A11: 10 | B11: sample | C11: EU | emb mid (p47-73) | D11: EU | E11: embedding | F11: 0.3532 | G11: 60.9 | J11: onregelmatigheden
A12: 11 | B12: sample | C12: NL | emb high (p73-100) | D12: NL | E12: embedding | F12: 0.4014 | G12: 73.7 | J12: bijstand
A13: 12 | B13: census | C13: census | D13: EU+NL | E13: embedding | F13: 0.4161 | G13: 77.6 | H13: 9 | I13: 9 | J13: toestemming
A14: 13 | B14: census | C14: census | D14: EU+NL | E14: phrase | F14: 1 | H14: 2 | I14: 33 | J14: voorschriften
A15: 14 | B15: sample | C15: EU | emb mid (p47-73) | D15: EU | E15: embedding | F15: 0.3851 | G15: 69.4 | J15: aanmelding
A16: 15 | B16: sample | C16: EU | phrase | D16: EU | E16: phrase | F16: 0.8 | J16: verordening
A17: 16 | B17: sample | C17: EU | head + compound | D17: EU | E17: head | F17: 0.8 | J17: vertaling van relevante informatie
A18: 17 | B18: sample | C18: NL | emb low (p20-47) | D18: NL | E18: embedding | F18: 0.258 | G18: 35.5 | J18: erkenning
A19: 18 | B19: sample | C19: EU | emb high (p73-100) | D19: EU | E19: embedding | F19: 0.4423 | G19: 84.6 | J19: verzoek
A20: 19 | B20: sample | C20: EU | emb low (p20-47) | D20: EU | E20: embedding | F20: 0.2044 | G20: 21.2 | J20: geaggregeerde beoordeling van het volwassenheidsniveau van de cyberbeveiligingscapaciteiten en -middelen in de hele Unie, met inbegrip van die op sectorniveau
A21: 20 | B21: sample | C21: EU | emb low (p20-47) | D21: EU | E21: embedding | F21: 0.2301 | G21: 28 | J21: elementen
A22: 21 | B22: sample | C22: NL | emb high (p73-100) | D22: NL | E22: embedding | F22: 0.4877 | G22: 96.7 | J22: bevoegde autoriteit
A23: 22 | B23: sample | C23: EU | emb mid (p47-73) | D23: EU | E23: embedding | F23: 0.3399 | G23: 57.3 | J23: AI-bureau
A24: 23 | B24: sample | C24: EU | emb high (p73-100) | D24: EU | E24: embedding | F24: 0.4591 | G24: 89.1 | J24: risico
A25: 24 | B25: census | C25: census | D25: EU | E25: embedding | F25: 0.4236 | G25: 79.6 | H25: 24 | I25: 0 | J25: uitvoeringshandelingen
A26: 25 | B26: sample | C26: NL | emb high (p73-100) | D26: NL | E26: embedding | F26: 0.401 | G26: 73.6 | J26: effecten van de wijziging in de praktijk
A27: 26 | B27: census | C27: census | D27: EU+NL | E27: embedding | F27: 0.3601 | G27: 62.7 | H27: 18 | I27: 9 | J27: maatregelen
A28: 27 | B28: sample | C28: EU | emb low (p20-47) | D28: EU | E28: embedding | F28: 0.2301 | G28: 28 | J28: elementen
A29: 28 | B29: sample | C29: NL | phrase | D29: NL | E29: phrase | F29: 1 | J29: veiling
A30: 29 | B30: sample | C30: NL | emb low (p20-47) | D30: NL | E30: embedding | F30: 0.2602 | G30: 36.1 | J30: bindende aanwijzing
A31: 30 | B31: sample | C31: EU | emb high (p73-100) | D31: EU | E31: embedding | F31: 0.4267 | G31: 80.5 | J31: belanghebbenden
A32: 31 | B32: sample | C32: NL | emb low (p20-47) | D32: NL | E32: embedding | F32: 0.2193 | G32: 25.1 | J32: gebruik laten maken van deze werken
A33: 32 | B33: sample | C33: EU | emb low (p20-47) | D33: EU | E33: embedding | F33: 0.2041 | G33: 21.1 | J33: omvang
A34: 33 | B34: census | C34: census | D34: EU+NL | E34: phrase | F34: 1 | H34: 9 | I34: 29 | J34: verplichting
A35: 34 | B35: sample | C35: NL | emb low (p20-47) | D35: NL | E35: embedding | F35: 0.2023 | G35: 20.6 | J35: effectieve procedure om onjuiste informatie te melden
A36: 35 | B36: sample | C36: EU | emb high (p73-100) | D36: EU | E36: embedding | F36: 0.4247 | G36: 79.9 | J36: aanvullende verklaring
A37: 36 | B37: sample | C37: EU | emb low (p20-47) | D37: EU | E37: embedding | F37: 0.211 | G37: 22.9 | J37: latere wijzigingen
A38: 37 | B38: sample | C38: NL | head + compound | D38: NL | E38: head | F38: 0.8 | J38: informatie, alsmede informatie of kan worden verkregen
A39: 38 | B39: sample | C39: NL | emb mid (p47-73) | D39: NL | E39: embedding | F39: 0.3835 | G39: 68.9 | J39: nummergebruikers
A40: 39 | B40: sample | C40: EU | emb high (p73-100) | D40: EU | E40: embedding | F40: 0.4071 | G40: 75.2 | J40: automatische waarschuwingsmechanismen
A41: 40 | B41: sample | C41: EU | phrase | D41: EU | E41: phrase | F41: 1 | J41: adviezen
A42: 41 | B42: sample | C42: EU | emb high (p73-100) | D42: EU | E42: embedding | F42: 0.4356 | G42: 82.8 | J42: uittreksels
A43: 42 | B43: sample | C43: NL | emb high (p73-100) | D43: NL | E43: embedding | F43: 0.4131 | G43: 76.8 | J43: persoonsgegevens van een abonnee
A44: 43 | B44: sample | C44: NL | emb mid (p47-73) | D44: NL | E44: embedding | F44: 0.3545 | G44: 61.2 | J44: afspraken
A45: 44 | B45: census | C45: census | D45: EU+NL | E45: phrase | F45: 1 | H45: 34 | I45: 3 | J45: verslag
A46: 45 | B46: sample | C46: NL | phrase | D46: NL | E46: phrase | F46: 1 | J46: aanbieder
A47: 46 | B47: sample | C47: EU | head + compound | D47: EU | E47: head | F47: 0.8 | J47: risicobeoordeling van het incident en corrigerende maatregelen
A48: 47 | B48: census | C48: census | D48: EU+NL | E48: phrase | F48: 1 | H48: 23 | I48: 6 | J48: advies
A49: 48 | B49: census | C49: census | D49: EU+NL | E49: embedding | F49: 0.4787 | G49: 94.3 | H49: 9 | I49: 15 | J49: bevoegdheden
A50: 49 | B50: sample | C50: NL | phrase | D50: NL | E50: phrase | F50: 1 | J50: pseudonimisering
A51: 50 | B51: sample | C51: EU | emb mid (p47-73) | D51: EU | E51: embedding | F51: 0.3833 | G51: 68.9 | J51: of aan de toezichtvoorwaarden voor het sluiten van het contract is voldaan
A52: 51 | B52: sample | C52: NL | emb high (p73-100) | D52: NL | E52: embedding | F52: 0.4323 | G52: 81.9 | J52: kennis
A53: 52 | B53: sample | C53: NL | emb low (p20-47) | D53: NL | E53: embedding | F53: 0.2743 | G53: 39.8 | J53: nummer
A54: 53 | B54: sample | C54: NL | emb high (p73-100) | D54: NL | E54: embedding | F54: 0.4161 | G54: 77.6 | J54: wijze de mededeling wordt gedaan
A55: 54 | B55: sample | C55: EU | emb low (p20-47) | D55: EU | E55: embedding | F55: 0.2465 | G55: 32.4 | J55: vertegenwoordigers van de financiële entiteit
A56: 55 | B56: sample | C56: EU | emb mid (p47-73) | D56: EU | E56: embedding | F56: 0.3291 | G56: 54.4 | J56: kennelijk ongegronde of buitensporige aard van het verzoek
A57: 56 | B57: sample | C57: EU | head + compound | D57: EU | E57: head | F57: 0.8 | J57: kritieke derde aanbieder van ICT-diensten
A58: 57 | B58: sample | C58: NL | emb low (p20-47) | D58: NL | E58: embedding | F58: 0.2293 | G58: 27.8 | J58: billijke en niet-discriminerende eisen
A59: 58 | B59: sample | C59: NL | emb high (p73-100) | D59: NL | E59: embedding | F59: 0.4046 | G59: 74.5 | J59: automatische oproep- en communicatiesystemen zonder menselijke tussenkomst, faxen en elektronische berichten
A60: 59 | B60: sample | C60: EU | emb low (p20-47) | D60: EU | E60: embedding | F60: 0.266 | G60: 37.6 | J60: of de maatregel gerechtvaardigd is
A61: 60 | B61: sample | C61: EU | emb mid (p47-73) | D61: EU | E61: embedding | F61: 0.3451 | G61: 58.7 | J61: passende en evenredige technische, operationele en organisatorische maatregelen
A62: 61 | B62: sample | C62: EU | head + compound | D62: EU | E62: head | F62: 0.8 | J62: derde aanbieder van ICT-diensten
A63: 62 | B63: sample | C63: NL | emb high (p73-100) | D63: NL | E63: embedding | F63: 0.4595 | G63: 89.2 | J63: ontheffing
A64: 63 | B64: sample | C64: NL | head + compound | D64: NL | E64: head | F64: 0.8 | J64: opgelegde verplichting
A65: 64 | B65: sample | C65: NL | phrase | D65: NL | E65: phrase | F65: 1 | J65: vergoeding
A66: 65 | B66: sample | C66: NL | emb mid (p47-73) | D66: NL | E66: embedding | F66: 0.3235 | G66: 52.9 | J66: last onder bestuursdwang
A67: 66 | B67: sample | C67: NL | emb low (p20-47) | D67: NL | E67: embedding | F67: 0.258 | G67: 35.5 | J67: erkenning
A68: 67 | B68: census | C68: census | D68: EU | E68: embedding | F68: 0.3492 | G68: 59.8 | H68: 19 | I68: 0 | J68: Commissie
A69: 68 | B69: sample | C69: NL | emb low (p20-47) | D69: NL | E69: embedding | F69: 0.2251 | G69: 26.7 | J69: attributen
A70: 69 | B70: sample | C70: EU | emb low (p20-47) | D70: EU | E70: embedding | F70: 0.2818 | G70: 41.8 | J70: risico van belangenconflicten met betrekking tot de aangewezen cyberbeveiligingsdeskundigen
A71: 70 | B71: sample | C71: EU | emb high (p73-100) | D71: EU | E71: embedding | F71: 0.4237 | G71: 79.7 | J71: toezichthoudende autoriteit
A72: 71 | B72: sample | C72: EU | emb high (p73-100) | D72: EU | E72: embedding | F72: 0.4805 | G72: 94.8 | J72: Persoonsgegevens
A73: 72 | B73: sample | C73: NL | head + compound | D73: NL | E73: head | F73: 0.64 | J73: besluit over de geschilbeslechting
A74: 73 | B74: sample | C74: NL | phrase | D74: NL | E74: phrase | F74: 1 | J74: vergoeding
A75: 74 | B75: sample | C75: EU | head + compound | D75: EU | E75: compound | F75: 0.6 | J75: binnen het toepassingsgebied vallende entiteiten en, indien van toepassing, andere entiteiten, op vrijwillige basis onderling relevante informatie over cyberbeveiliging kunnen uitwisselen, met inbegrip van informatie over cyberdreigingen, bijna-incidenten, kwetsbaarheden, technieken en procedures, indicatoren voor aantasting, vijandige tactieken, dreigingsactorspecifieke informatie, cyberbeveiligingswaarschuwingen en aanbevelingen betreffende de configuratie van cyberbeveiligingsinstrumenten om cyberaanvallen te detecteren
A76: 75 | B76: sample | C76: EU | emb low (p20-47) | D76: EU | E76: embedding | F76: 0.2762 | G76: 40.3 | J76: door andere toezichthoudende autoriteiten gevraagde informatie
A77: 76 | B77: sample | C77: EU | emb mid (p47-73) | D77: EU | E77: embedding | F77: 0.3278 | G77: 54.1 | J77: gemachtigde
A78: 77 | B78: sample | C78: NL | emb low (p20-47) | D78: NL | E78: embedding | F78: 0.2308 | G78: 28.2 | J78: overige taken
A79: 78 | B79: census | C79: census | D79: EU+NL | E79: embedding | F79: 0.4625 | G79: 90 | H79: 10 | I79: 34 | J79: gegevens
A80: 79 | B80: sample | C80: EU | emb mid (p47-73) | D80: EU | E80: embedding | F80: 0.334 | G80: 55.7 | J80: financiële entiteit
A81: 80 | B81: sample | C81: EU | emb mid (p47-73) | D81: EU | E81: embedding | F81: 0.3336 | G81: 55.6 | J81: voldoende middelen
A82: 81 | B82: sample | C82: EU | emb mid (p47-73) | D82: EU | E82: embedding | F82: 0.351 | G82: 60.3 | J82: secretariaat van de AI-board
A83: 82 | B83: sample | C83: NL | emb mid (p47-73) | D83: NL | E83: embedding | F83: 0.3393 | G83: 57.1 | J83: beperkingen
A84: 83 | B84: census | C84: census | D84: EU+NL | E84: embedding | F84: 0.417 | G84: 77.9 | H84: 7 | I84: 85 | J84: regels
A85: 84 | B85: sample | C85: EU | head + compound | D85: EU | E85: compound | F85: 0.6 | J85: transparantieverplichtingen
A86: 85 | B86: sample | C86: EU | phrase | D86: EU | E86: phrase | F86: 1 | J86: schade
A87: 86 | B87: sample | C87: EU | emb high (p73-100) | D87: EU | E87: embedding | F87: 0.4393 | G87: 83.8 | J87: kosten
A88: 87 | B88: sample | C88: EU | phrase | D88: EU | E88: phrase | F88: 1 | J88: vertrouwelijke informatie
A89: 88 | B89: census | C89: census | D89: EU+NL | E89: phrase | F89: 0.8 | H89: 27 | I89: 22 | J89: besluit
A90: 89 | B90: sample | C90: NL | emb mid (p47-73) | D90: NL | E90: embedding | F90: 0.3259 | G90: 53.6 | J90: beëindiging van de status gekwalificeerd
A91: 90 | B91: sample | C91: NL | emb high (p73-100) | D91: NL | E91: embedding | F91: 0.4655 | G91: 90.8 | J91: verwerking van verkeersgegevens
A92: 91 | B92: sample | C92: EU | head + compound | D92: EU | E92: head | F92: 0.8 | J92: verslag over haar bevindingen
A93: 92 | B93: sample | C93: NL | emb mid (p47-73) | D93: NL | E93: embedding | F93: 0.3105 | G93: 49.5 | J93: kwetsbaarheden
A94: 93 | B94: sample | C94: EU | head + compound | D94: EU | E94: head | F94: 0.8 | J94: administratieve geldboeten
A95: 94 | B95: sample | C95: NL | emb low (p20-47) | D95: NL | E95: embedding | F95: 0.2865 | G95: 43.1 | J95: verbod op het houden of verkrijgen van overwegende zeggenschap
A96: 95 | B96: sample | C96: EU | phrase | D96: EU | E96: phrase | F96: 1 | J96: dwangsom
A97: 96 | B97: sample | C97: NL | phrase | D97: NL | E97: phrase | F97: 1 | J97: voorschrift
A98: 97 | B98: census | C98: census | D98: NL | E98: embedding | F98: 0.4775 | G98: 94 | H98: 0 | I98: 18 | J98: bestuurlijke boete
A99: 98 | B99: sample | C99: EU | emb high (p73-100) | D99: EU | E99: embedding | F99: 0.4814 | G99: 95 | J99: bevoegdheid
A100: 99 | B100: sample | C100: EU | phrase | D100: EU | E100: phrase | F100: 1 | J100: natuurlijke personen
...

Sheet Design
A1: Sample design
A2: What is estimated. The share of norm objects whose EuroVoc mapping is right, for EU law and for Dutch law, and the difference between the two. The sampling unit is therefore an object unit as it occurs in a norm, not a distinct string: a text used in 90 norms counts 90 times, as it does downstream, and each sampled unit is judged in the context of its own norm. Why these strata. Source (EU / NL) is a stratum because it is the comparison of interest; stratifying guarantees both sources get the same number of judgements regardless of their share. Within a source the strata follow the mapping cascade, because each level makes a different kind of claim and is expected to fail at a different rate: phrase (exact label), head + compound (lexical match on part of the object; compound is merged with head because it holds only 43 EU and 12 Dutch units, too few to estimate on its own), and the embedding matches split into three equal bands above the fallback percentile (20). Embedding matches are 80.7% of sampled EU units and 84.2% of Dutch ones, so their confidence bands carry most of the weight. Why these sizes. 50 judgements per source: the floor of 8 per cell keeps every cell measured, and the rest goes to the embedding bands in proportion to their size, because that is where the weight is. At 50% precision in every cell this gives about +/-13 points for EU law and +/-11 for Dutch law, and about +/-17 points on the EU - NL difference; only differences of roughly 24 points or more can be detected reliably (80% power). The sample is not proportional, so overall figures are weighted by N_h (the 'review' step), never by row count. What is left out. Unmapped units and norms whose object was dropped make no mapping claim; their shares are exact counts (table below). Norms without any object never reach the mapping. Optional checks of these, if drawn, are reported separately and never enter the precision figures.
A4: stratum | B4: source | C4: population N_h (unit occurrences) | D4: share of source's mapped units | E4: n judged | F4: why this stratum and this n
A5: EU | census | B5: EU | C5: 309 | D5: =IFERROR(C5/SUMIF($B$5:$B$16,B5,$C$5:$C$16),0) -> 0.12189349 | E5: 20 | F5: Occurrences of the 20 census texts in EU law; each text is judged once (shared with the other source).
A6: EU | phrase | B6: EU | C6: 111 | D6: =IFERROR(C6/SUMIF($B$5:$B$16,B6,$C$5:$C$16),0) -> 0.043786982 | E6: 8 | F6: Exact label match; expected to be the most reliable level. Floor only.
A7: EU | head + compound | B7: EU | C7: 318 | D7: =IFERROR(C7/SUMIF($B$5:$B$16,B7,$C$5:$C$16),0) -> 0.12544379 | E7: 8 | F7: Lexical match on part of the object (head word or compound part). Compound merged in: too few units to stand alone. Floor only.
A8: EU | emb low (p20-47) | B8: EU | C8: 570 | D8: =IFERROR(C8/SUMIF($B$5:$B$16,B8,$C$5:$C$16),0) -> 0.22485207 | E8: 11 | F8: Embedding match, lowest confidence band. Floor plus a share of the rest in proportion to its size.
A9: EU | emb mid (p47-73) | B9: EU | C9: 646 | D9: =IFERROR(C9/SUMIF($B$5:$B$16,B9,$C$5:$C$16),0) -> 0.25483235 | E9: 12 | F9: Embedding match, middle confidence band. Floor plus a share of the rest in proportion to its size.
A10: EU | emb high (p73-100) | B10: EU | C10: 581 | D10: =IFERROR(C10/SUMIF($B$5:$B$16,B10,$C$5:$C$16),0) -> 0.22919132 | E10: 11 | F10: Embedding match, highest confidence band. Floor plus a share of the rest in proportion to its size.
A11: NL | census | B11: NL | C11: 406 | D11: =IFERROR(C11/SUMIF($B$5:$B$16,B11,$C$5:$C$16),0) -> 0.22924901 | E11: 20 | F11: Occurrences of the 20 census texts in NL law; each text is judged once (shared with the other source).
A12: NL | phrase | B12: NL | C12: 55 | D12: =IFERROR(C12/SUMIF($B$5:$B$16,B12,$C$5:$C$16),0) -> 0.031055901 | E12: 8 | F12: Exact label match; expected to be the most reliable level. Floor only.
A13: NL | head + compound | B13: NL | C13: 161 | D13: =IFERROR(C13/SUMIF($B$5:$B$16,B13,$C$5:$C$16),0) -> 0.090909091 | E13: 8 | F13: Lexical match on part of the object (head word or compound part). Compound merged in: too few units to stand alone. Floor only.
A14: NL | emb low (p20-47) | B14: NL | C14: 371 | D14: =IFERROR(C14/SUMIF($B$5:$B$16,B14,$C$5:$C$16),0) -> 0.20948617 | E14: 11 | F14: Embedding match, lowest confidence band. Floor plus a share of the rest in proportion to its size.
A15: NL | emb mid (p47-73) | B15: NL | C15: 364 | D15: =IFERROR(C15/SUMIF($B$5:$B$16,B15,$C$5:$C$16),0) -> 0.2055336 | E15: 11 | F15: Embedding match, middle confidence band. Floor plus a share of the rest in proportion to its size.
A16: NL | emb high (p73-100) | B16: NL | C16: 414 | D16: =IFERROR(C16/SUMIF($B$5:$B$16,B16,$C$5:$C$16),0) -> 0.23376623 | E16: 12 | F16: Embedding match, highest confidence band. Floor plus a share of the rest in proportion to its size.
A18: Exact counts (no sampling)
B19: EU | C19: NL
A20: norms | B20: 3109 | C20: 2150
A21: object units | B21: 2936 | C21: 2020
A22: mapped units | B22: 2535 | C22: 1771
A23: unmapped units | B23: 401 | C23: 249
A24: norms with object dropped (no unit) | B24: 126 | C24: 138
A25: norms without any object | B25: 347 | C25: 149
A26: unmapped share of units | B26: =IFERROR(B23/B21,0) -> 0.13658038 | C26: =IFERROR(C23/C21,0) -> 0.12326733
A27: dropped share of norms | B27: =IFERROR(B24/B20,0) -> 0.040527501 | C27: =IFERROR(C24/C20,0) -> 0.064186047
A29: Census of frequent texts
A30: Why a census of the 20 most frequent texts. The mapping is computed per text, so one judgement settles every occurrence of a text, and an error in a frequent text repeats in every norm that uses it. The object texts are heavy-tailed: most occur once, a few occur dozens of times. A random sample of this size would draw the frequent texts by chance or not at all, which makes the estimate swing on luck; judging them all removes that part of the sampling error at the cost of one judgement each. How the texts were chosen. Not by hand: the texts are the top of the frequency ranking of mapped unit occurrences (all sources together), ties broken alphabetically, fixed before any judging. In particular they were not chosen because their mapping looked right or wrong, which would bias the estimate. The table lists each text with its counts. Why 20. Coverage grows quickly over the first texts and then flattens (coverage table to the right): the census costs one judgement per text, so it stops where a further text covers little more than a sampled unit would. It matters most for Dutch law, whose fixed formulas (e.g. 'nadere regels', 'regels') make a few texts a large share of all objects; leaving them to chance would make the EU - NL comparison depend on whether they happened to be drawn. How to judge a census row. Several contexts are shown, taken in turn from both sources. Judge the mapping for the way the text is used in them; if it fits some uses but not others, choose 'partial' and say so in the notes.
A32: rank | B32: text | C32: EU occurrences | D32: NL occurrences | E32: total | F32: share of all mapped units | G32: cumulative share | H32: why this text | J32: census size | K32: EU coverage | L32: NL coverage
A33: 1 | B33: regels | C33: 7 | D33: 85 | E33: =C33+D33 -> 92 | F33: =E33/4306 -> 0.021365536 | G33: =SUM($E$33:E33)/4306 -> 0.021365536 | H33: Frequency rank 1 of 2,359 distinct texts; used in both sources (mostly Dutch). One judgement covers its 92 norm occurrences. | J33: 5 | K33: 0.042209073 | L33: 0.12365895
A34: 2 | B34: informatie | C34: 62 | D34: 25 | E34: =C34+D34 -> 87 | F34: =E34/4306 -> 0.020204366 | G34: =SUM($E$33:E34)/4306 -> 0.041569902 | H34: Frequency rank 2 of 2,359 distinct texts; used in both sources (mostly EU). One judgement covers its 87 norm occurrences. | J34: 10 | K34: 0.077317554 | L34: 0.16770186
A35: 3 | B35: nadere regels | C35: 1 | D35: 53 | E35: =C35+D35 -> 54 | F35: =E35/4306 -> 0.012540641 | G35: =SUM($E$33:E35)/4306 -> 0.054110543 | H35: Frequency rank 3 of 2,359 distinct texts; used in both sources (mostly Dutch). One judgement covers its 54 norm occurrences. | J35: 20 | K35: 0.12189349 | L35: 0.22924901
A36: 4 | B36: besluit | C36: 27 | D36: 22 | E36: =C36+D36 -> 49 | F36: =E36/4306 -> 0.011379471 | G36: =SUM($E$33:E36)/4306 -> 0.065490014 | H36: Frequency rank 4 of 2,359 distinct texts; used in both sources (balanced). One judgement covers its 49 norm occurrences. | J36: 30 | K36: 0.15384615 | L36: 0.2676454
A37: 5 | B37: gegevens | C37: 10 | D37: 34 | E37: =C37+D37 -> 44 | F37: =E37/4306 -> 0.0102183 | G37: =SUM($E$33:E37)/4306 -> 0.075708314 | H37: Frequency rank 5 of 2,359 distinct texts; used in both sources (mostly Dutch). One judgement covers its 44 norm occurrences. | J37: 50 | K37: 0.19289941 | L37: 0.32523998
A38: 6 | B38: verplichting | C38: 9 | D38: 29 | E38: =C38+D38 -> 38 | F38: =E38/4306 -> 0.0088248955 | G38: =SUM($E$33:E38)/4306 -> 0.084533209 | H38: Frequency rank 6 of 2,359 distinct texts; used in both sources (mostly Dutch). One judgement covers its 38 norm occurrences. | J38: 100 | K38: 0.26666667 | L38: 0.39695088
A39: 7 | B39: verslag | C39: 34 | D39: 3 | E39: =C39+D39 -> 37 | F39: =E39/4306 -> 0.0085926614 | G39: =SUM($E$33:E39)/4306 -> 0.093125871 | H39: Frequency rank 7 of 2,359 distinct texts; used in both sources (mostly EU). One judgement covers its 37 norm occurrences.
A40: 8 | B40: voorschriften | C40: 2 | D40: 33 | E40: =C40+D40 -> 35 | F40: =E40/4306 -> 0.0081281932 | G40: =SUM($E$33:E40)/4306 -> 0.10125406 | H40: Frequency rank 8 of 2,359 distinct texts; used in both sources (mostly Dutch). One judgement covers its 35 norm occurrences.
A41: 9 | B41: advies | C41: 23 | D41: 6 | E41: =C41+D41 -> 29 | F41: =E41/4306 -> 0.0067347887 | G41: =SUM($E$33:E41)/4306 -> 0.10798885 | H41: Frequency rank 9 of 2,359 distinct texts; used in both sources (mostly EU). One judgement covers its 29 norm occurrences.
A42: 10 | B42: persoonsgegevens | C42: 21 | D42: 7 | E42: =C42+D42 -> 28 | F42: =E42/4306 -> 0.0065025546 | G42: =SUM($E$33:E42)/4306 -> 0.11449141 | H42: Frequency rank 10 of 2,359 distinct texts; used in both sources (mostly EU). One judgement covers its 28 norm occurrences.
A43: 11 | B43: maatregelen | C43: 18 | D43: 9 | E43: =C43+D43 -> 27 | F43: =E43/4306 -> 0.0062703205 | G43: =SUM($E$33:E43)/4306 -> 0.12076173 | H43: Frequency rank 11 of 2,359 distinct texts; used in both sources (mostly EU). One judgement covers its 27 norm occurrences.
A44: 12 | B44: verplichtingen | C44: 4 | D44: 23 | E44: =C44+D44 -> 27 | F44: =E44/4306 -> 0.0062703205 | G44: =SUM($E$33:E44)/4306 -> 0.12703205 | H44: Frequency rank 12 of 2,359 distinct texts; used in both sources (mostly Dutch). One judgement covers its 27 norm occurrences.
A45: 13 | B45: bevoegdheden | C45: 9 | D45: 15 | E45: =C45+D45 -> 24 | F45: =E45/4306 -> 0.0055736182 | G45: =SUM($E$33:E45)/4306 -> 0.13260567 | H45: Frequency rank 13 of 2,359 distinct texts; used in both sources (balanced). One judgement covers its 24 norm occurrences.
A46: 14 | B46: uitvoeringshandelingen | C46: 24 | D46: 0 | E46: =C46+D46 -> 24 | F46: =E46/4306 -> 0.0055736182 | G46: =SUM($E$33:E46)/4306 -> 0.13817928 | H46: Frequency rank 14 of 2,359 distinct texts; used only in EU law. One judgement covers its 24 norm occurrences.
A47: 15 | B47: termijn | C47: 10 | D47: 13 | E47: =C47+D47 -> 23 | F47: =E47/4306 -> 0.0053413841 | G47: =SUM($E$33:E47)/4306 -> 0.14352067 | H47: Frequency rank 15 of 2,359 distinct texts; used in both sources (balanced). One judgement covers its 23 norm occurrences.
A48: 16 | B48: vergunning | C48: 1 | D48: 22 | E48: =C48+D48 -> 23 | F48: =E48/4306 -> 0.0053413841 | G48: =SUM($E$33:E48)/4306 -> 0.14886205 | H48: Frequency rank 16 of 2,359 distinct texts; used in both sources (mostly Dutch). One judgement covers its 23 norm occurrences.
A49: 17 | B49: Commissie | C49: 19 | D49: 0 | E49: =C49+D49 -> 19 | F49: =E49/4306 -> 0.0044124477 | G49: =SUM($E$33:E49)/4306 -> 0.1532745 | H49: Frequency rank 17 of 2,359 distinct texts; used only in EU law. One judgement covers its 19 norm occurrences.
A50: 18 | B50: gedelegeerde handelingen | C50: 19 | D50: 0 | E50: =C50+D50 -> 19 | F50: =E50/4306 -> 0.0044124477 | G50: =SUM($E$33:E50)/4306 -> 0.15768695 | H50: Frequency rank 18 of 2,359 distinct texts; used only in EU law. One judgement covers its 19 norm occurrences.
... A52: 20 | B52: toestemming | C52: 9 | D52: 9 | E52: =C52+D52 -> 18 | F52: =E52/4306 -> 0.0041802137 | G52: =SUM($E$33:E52)/4306 -> 0.16604738 | H52: Frequency rank 20 of 2,359 distinct texts; used in both sources (balanced). One judgement covers its 18 norm occurrences.
B53: first text left out: 'aanwijzing' (17 occurrences)

Sheet Summary
A1: stratum | B1: population N_h | C1: rows | D1: judged | E1: correct | F1: partial | G1: wrong | H1: unclear | I1: precision strict | J1: precision lenient | K1: strict 95% low | L1: strict 95% high | N1: z
A2: census | B2: 20 | C2: =COUNTIFS(key!$C$2:$C$121,A2) -> 20 | D2: =COUNTIFS(key!$C$2:$C$121,A2,Validate!$I$2:$I$121,"<>") -> 0 | E2: =COUNTIFS(key!$C$2:$C$121,A2,Validate!$I$2:$I$121,"correct") -> 0 | F2: =COUNTIFS(key!$C$2:$C$121,A2,Validate!$I$2:$I$121,"partial") -> 0 | G2: =COUNTIFS(key!$C$2:$C$121,A2,Validate!$I$2:$I$121,"wrong") -> 0 | H2: =COUNTIFS(key!$C$2:$C$121,A2,Validate!$I$2:$I$121,"unclear") -> 0 | I2: =IFERROR(E2/(D2-H2),"") | J2: =IFERROR((E2+F2)/(D2-H2),"") | K2: =IFERROR(MAX(0,(I2+$N$2^2/(2*(D2-H2)))/(1+$N$2^2/(D2-H2))-$N$2*SQRT(I2*(1-I2)/(D2-H2)+$N$2^2/(4*(D2-H2)^2))/(1+$N$2^2/(D2-H2))),"") | L2: =IFERROR(MIN(1,(I2+$N$2^2/(2*(D2-H2)))/(1+$N$2^2/(D2-H2))+$N$2*SQRT(I2*(1-I2)/(D2-H2)+$N$2^2/(4*(D2-H2)^2))/(1+$N$2^2/(D2-H2))),"") | N2: 1.96
A3: EU | phrase | B3: 111 | C3: =COUNTIFS(key!$C$2:$C$121,A3) -> 8 | D3: =COUNTIFS(key!$C$2:$C$121,A3,Validate!$I$2:$I$121,"<>") -> 0 | E3: =COUNTIFS(key!$C$2:$C$121,A3,Validate!$I$2:$I$121,"correct") -> 0 | F3: =COUNTIFS(key!$C$2:$C$121,A3,Validate!$I$2:$I$121,"partial") -> 0 | G3: =COUNTIFS(key!$C$2:$C$121,A3,Validate!$I$2:$I$121,"wrong") -> 0 | H3: =COUNTIFS(key!$C$2:$C$121,A3,Validate!$I$2:$I$121,"unclear") -> 0 | I3: =IFERROR(E3/(D3-H3),"") | J3: =IFERROR((E3+F3)/(D3-H3),"") | K3: =IFERROR(MAX(0,(I3+$N$2^2/(2*(D3-H3)))/(1+$N$2^2/(D3-H3))-$N$2*SQRT(I3*(1-I3)/(D3-H3)+$N$2^2/(4*(D3-H3)^2))/(1+$N$2^2/(D3-H3))),"") | L3: =IFERROR(MIN(1,(I3+$N$2^2/(2*(D3-H3)))/(1+$N$2^2/(D3-H3))+$N$2*SQRT(I3*(1-I3)/(D3-H3)+$N$2^2/(4*(D3-H3)^2))/(1+$N$2^2/(D3-H3))),"")
A4: EU | head + compound | B4: 318 | C4: =COUNTIFS(key!$C$2:$C$121,A4) -> 8 | D4: =COUNTIFS(key!$C$2:$C$121,A4,Validate!$I$2:$I$121,"<>") -> 0 | E4: =COUNTIFS(key!$C$2:$C$121,A4,Validate!$I$2:$I$121,"correct") -> 0 | F4: =COUNTIFS(key!$C$2:$C$121,A4,Validate!$I$2:$I$121,"partial") -> 0 | G4: =COUNTIFS(key!$C$2:$C$121,A4,Validate!$I$2:$I$121,"wrong") -> 0 | H4: =COUNTIFS(key!$C$2:$C$121,A4,Validate!$I$2:$I$121,"unclear") -> 0 | I4: =IFERROR(E4/(D4-H4),"") | J4: =IFERROR((E4+F4)/(D4-H4),"") | K4: =IFERROR(MAX(0,(I4+$N$2^2/(2*(D4-H4)))/(1+$N$2^2/(D4-H4))-$N$2*SQRT(I4*(1-I4)/(D4-H4)+$N$2^2/(4*(D4-H4)^2))/(1+$N$2^2/(D4-H4))),"") | L4: =IFERROR(MIN(1,(I4+$N$2^2/(2*(D4-H4)))/(1+$N$2^2/(D4-H4))+$N$2*SQRT(I4*(1-I4)/(D4-H4)+$N$2^2/(4*(D4-H4)^2))/(1+$N$2^2/(D4-H4))),"")
A5: EU | emb low (p20-47) | B5: 570 | C5: =COUNTIFS(key!$C$2:$C$121,A5) -> 11 | D5: =COUNTIFS(key!$C$2:$C$121,A5,Validate!$I$2:$I$121,"<>") -> 0 | E5: =COUNTIFS(key!$C$2:$C$121,A5,Validate!$I$2:$I$121,"correct") -> 0 | F5: =COUNTIFS(key!$C$2:$C$121,A5,Validate!$I$2:$I$121,"partial") -> 0 | G5: =COUNTIFS(key!$C$2:$C$121,A5,Validate!$I$2:$I$121,"wrong") -> 0 | H5: =COUNTIFS(key!$C$2:$C$121,A5,Validate!$I$2:$I$121,"unclear") -> 0 | I5: =IFERROR(E5/(D5-H5),"") | J5: =IFERROR((E5+F5)/(D5-H5),"") | K5: =IFERROR(MAX(0,(I5+$N$2^2/(2*(D5-H5)))/(1+$N$2^2/(D5-H5))-$N$2*SQRT(I5*(1-I5)/(D5-H5)+$N$2^2/(4*(D5-H5)^2))/(1+$N$2^2/(D5-H5))),"") | L5: =IFERROR(MIN(1,(I5+$N$2^2/(2*(D5-H5)))/(1+$N$2^2/(D5-H5))+$N$2*SQRT(I5*(1-I5)/(D5-H5)+$N$2^2/(4*(D5-H5)^2))/(1+$N$2^2/(D5-H5))),"")
A6: EU | emb mid (p47-73) | B6: 646 | C6: =COUNTIFS(key!$C$2:$C$121,A6) -> 12 | D6: =COUNTIFS(key!$C$2:$C$121,A6,Validate!$I$2:$I$121,"<>") -> 0 | E6: =COUNTIFS(key!$C$2:$C$121,A6,Validate!$I$2:$I$121,"correct") -> 0 | F6: =COUNTIFS(key!$C$2:$C$121,A6,Validate!$I$2:$I$121,"partial") -> 0 | G6: =COUNTIFS(key!$C$2:$C$121,A6,Validate!$I$2:$I$121,"wrong") -> 0 | H6: =COUNTIFS(key!$C$2:$C$121,A6,Validate!$I$2:$I$121,"unclear") -> 0 | I6: =IFERROR(E6/(D6-H6),"") | J6: =IFERROR((E6+F6)/(D6-H6),"") | K6: =IFERROR(MAX(0,(I6+$N$2^2/(2*(D6-H6)))/(1+$N$2^2/(D6-H6))-$N$2*SQRT(I6*(1-I6)/(D6-H6)+$N$2^2/(4*(D6-H6)^2))/(1+$N$2^2/(D6-H6))),"") | L6: =IFERROR(MIN(1,(I6+$N$2^2/(2*(D6-H6)))/(1+$N$2^2/(D6-H6))+$N$2*SQRT(I6*(1-I6)/(D6-H6)+$N$2^2/(4*(D6-H6)^2))/(1+$N$2^2/(D6-H6))),"")
A7: EU | emb high (p73-100) | B7: 581 | C7: =COUNTIFS(key!$C$2:$C$121,A7) -> 11 | D7: =COUNTIFS(key!$C$2:$C$121,A7,Validate!$I$2:$I$121,"<>") -> 0 | E7: =COUNTIFS(key!$C$2:$C$121,A7,Validate!$I$2:$I$121,"correct") -> 0 | F7: =COUNTIFS(key!$C$2:$C$121,A7,Validate!$I$2:$I$121,"partial") -> 0 | G7: =COUNTIFS(key!$C$2:$C$121,A7,Validate!$I$2:$I$121,"wrong") -> 0 | H7: =COUNTIFS(key!$C$2:$C$121,A7,Validate!$I$2:$I$121,"unclear") -> 0 | I7: =IFERROR(E7/(D7-H7),"") | J7: =IFERROR((E7+F7)/(D7-H7),"") | K7: =IFERROR(MAX(0,(I7+$N$2^2/(2*(D7-H7)))/(1+$N$2^2/(D7-H7))-$N$2*SQRT(I7*(1-I7)/(D7-H7)+$N$2^2/(4*(D7-H7)^2))/(1+$N$2^2/(D7-H7))),"") | L7: =IFERROR(MIN(1,(I7+$N$2^2/(2*(D7-H7)))/(1+$N$2^2/(D7-H7))+$N$2*SQRT(I7*(1-I7)/(D7-H7)+$N$2^2/(4*(D7-H7)^2))/(1+$N$2^2/(D7-H7))),"")
A8: NL | phrase | B8: 55 | C8: =COUNTIFS(key!$C$2:$C$121,A8) -> 8 | D8: =COUNTIFS(key!$C$2:$C$121,A8,Validate!$I$2:$I$121,"<>") -> 0 | E8: =COUNTIFS(key!$C$2:$C$121,A8,Validate!$I$2:$I$121,"correct") -> 0 | F8: =COUNTIFS(key!$C$2:$C$121,A8,Validate!$I$2:$I$121,"partial") -> 0 | G8: =COUNTIFS(key!$C$2:$C$121,A8,Validate!$I$2:$I$121,"wrong") -> 0 | H8: =COUNTIFS(key!$C$2:$C$121,A8,Validate!$I$2:$I$121,"unclear") -> 0 | I8: =IFERROR(E8/(D8-H8),"") | J8: =IFERROR((E8+F8)/(D8-H8),"") | K8: =IFERROR(MAX(0,(I8+$N$2^2/(2*(D8-H8)))/(1+$N$2^2/(D8-H8))-$N$2*SQRT(I8*(1-I8)/(D8-H8)+$N$2^2/(4*(D8-H8)^2))/(1+$N$2^2/(D8-H8))),"") | L8: =IFERROR(MIN(1,(I8+$N$2^2/(2*(D8-H8)))/(1+$N$2^2/(D8-H8))+$N$2*SQRT(I8*(1-I8)/(D8-H8)+$N$2^2/(4*(D8-H8)^2))/(1+$N$2^2/(D8-H8))),"")
A9: NL | head + compound | B9: 161 | C9: =COUNTIFS(key!$C$2:$C$121,A9) -> 8 | D9: =COUNTIFS(key!$C$2:$C$121,A9,Validate!$I$2:$I$121,"<>") -> 0 | E9: =COUNTIFS(key!$C$2:$C$121,A9,Validate!$I$2:$I$121,"correct") -> 0 | F9: =COUNTIFS(key!$C$2:$C$121,A9,Validate!$I$2:$I$121,"partial") -> 0 | G9: =COUNTIFS(key!$C$2:$C$121,A9,Validate!$I$2:$I$121,"wrong") -> 0 | H9: =COUNTIFS(key!$C$2:$C$121,A9,Validate!$I$2:$I$121,"unclear") -> 0 | I9: =IFERROR(E9/(D9-H9),"") | J9: =IFERROR((E9+F9)/(D9-H9),"") | K9: =IFERROR(MAX(0,(I9+$N$2^2/(2*(D9-H9)))/(1+$N$2^2/(D9-H9))-$N$2*SQRT(I9*(1-I9)/(D9-H9)+$N$2^2/(4*(D9-H9)^2))/(1+$N$2^2/(D9-H9))),"") | L9: =IFERROR(MIN(1,(I9+$N$2^2/(2*(D9-H9)))/(1+$N$2^2/(D9-H9))+$N$2*SQRT(I9*(1-I9)/(D9-H9)+$N$2^2/(4*(D9-H9)^2))/(1+$N$2^2/(D9-H9))),"")
A10: NL | emb low (p20-47) | B10: 371 | C10: =COUNTIFS(key!$C$2:$C$121,A10) -> 11 | D10: =COUNTIFS(key!$C$2:$C$121,A10,Validate!$I$2:$I$121,"<>") -> 0 | E10: =COUNTIFS(key!$C$2:$C$121,A10,Validate!$I$2:$I$121,"correct") -> 0 | F10: =COUNTIFS(key!$C$2:$C$121,A10,Validate!$I$2:$I$121,"partial") -> 0 | G10: =COUNTIFS(key!$C$2:$C$121,A10,Validate!$I$2:$I$121,"wrong") -> 0 | H10: =COUNTIFS(key!$C$2:$C$121,A10,Validate!$I$2:$I$121,"unclear") -> 0 | I10: =IFERROR(E10/(D10-H10),"") | J10: =IFERROR((E10+F10)/(D10-H10),"") | K10: =IFERROR(MAX(0,(I10+$N$2^2/(2*(D10-H10)))/(1+$N$2^2/(D10-H10))-$N$2*SQRT(I10*(1-I10)/(D10-H10)+$N$2^2/(4*(D10-H10)^2))/(1+$N$2^2/(D10-H10))),"") | L10: =IFERROR(MIN(1,(I10+$N$2^2/(2*(D10-H10)))/(1+$N$2^2/(D10-H10))+$N$2*SQRT(I10*(1-I10)/(D10-H10)+$N$2^2/(4*(D10-H10)^2))/(1+$N$2^2/(D10-H10))),"")
A11: NL | emb mid (p47-73) | B11: 364 | C11: =COUNTIFS(key!$C$2:$C$121,A11) -> 11 | D11: =COUNTIFS(key!$C$2:$C$121,A11,Validate!$I$2:$I$121,"<>") -> 0 | E11: =COUNTIFS(key!$C$2:$C$121,A11,Validate!$I$2:$I$121,"correct") -> 0 | F11: =COUNTIFS(key!$C$2:$C$121,A11,Validate!$I$2:$I$121,"partial") -> 0 | G11: =COUNTIFS(key!$C$2:$C$121,A11,Validate!$I$2:$I$121,"wrong") -> 0 | H11: =COUNTIFS(key!$C$2:$C$121,A11,Validate!$I$2:$I$121,"unclear") -> 0 | I11: =IFERROR(E11/(D11-H11),"") | J11: =IFERROR((E11+F11)/(D11-H11),"") | K11: =IFERROR(MAX(0,(I11+$N$2^2/(2*(D11-H11)))/(1+$N$2^2/(D11-H11))-$N$2*SQRT(I11*(1-I11)/(D11-H11)+$N$2^2/(4*(D11-H11)^2))/(1+$N$2^2/(D11-H11))),"") | L11: =IFERROR(MIN(1,(I11+$N$2^2/(2*(D11-H11)))/(1+$N$2^2/(D11-H11))+$N$2*SQRT(I11*(1-I11)/(D11-H11)+$N$2^2/(4*(D11-H11)^2))/(1+$N$2^2/(D11-H11))),"")
A12: NL | emb high (p73-100) | B12: 414 | C12: =COUNTIFS(key!$C$2:$C$121,A12) -> 12 | D12: =COUNTIFS(key!$C$2:$C$121,A12,Validate!$I$2:$I$121,"<>") -> 0 | E12: =COUNTIFS(key!$C$2:$C$121,A12,Validate!$I$2:$I$121,"correct") -> 0 | F12: =COUNTIFS(key!$C$2:$C$121,A12,Validate!$I$2:$I$121,"partial") -> 0 | G12: =COUNTIFS(key!$C$2:$C$121,A12,Validate!$I$2:$I$121,"wrong") -> 0 | H12: =COUNTIFS(key!$C$2:$C$121,A12,Validate!$I$2:$I$121,"unclear") -> 0 | I12: =IFERROR(E12/(D12-H12),"") | J12: =IFERROR((E12+F12)/(D12-H12),"") | K12: =IFERROR(MAX(0,(I12+$N$2^2/(2*(D12-H12)))/(1+$N$2^2/(D12-H12))-$N$2*SQRT(I12*(1-I12)/(D12-H12)+$N$2^2/(4*(D12-H12)^2))/(1+$N$2^2/(D12-H12))),"") | L12: =IFERROR(MIN(1,(I12+$N$2^2/(2*(D12-H12)))/(1+$N$2^2/(D12-H12))+$N$2*SQRT(I12*(1-I12)/(D12-H12)+$N$2^2/(4*(D12-H12)^2))/(1+$N$2^2/(D12-H12))),"")
A14: Per-stratum figures only; they are unweighted and the census row counts texts, not occurrences.
A15: Weighted precision per source, the EU - NL difference and the mix-adjusted comparison come from: python eurovoc_review.py review --xlsx <this file>
A16: Strict = correct; lenient = correct + partial; unclear is excluded. Intervals: Wilson, z in N2.
A17: Check strata (if any) measure whether leaving an object unmapped / dropping it was right; they never enter the precision totals.
